Workbook

Sheet Premissas
A1: ANTÉVIA — Premissas do Modelo Financeiro v1.0 | H1: Simples Nacional — Anexo III (2027–2028)
A3: Premissa | B3: Valor | C3: Unidade | D3: Tipo | E3: Status / observação | F3: Fonte | H3: RBT12 até (R$) | I3: Alíquota nominal | J3: Dedução (R$) | K3: Fonte
A4: Horizonte | B4: 12 | C4: trimestres | D4: Modelo | E4: 3 anos | F4: Sprint E6 | H4: 180000 | I4: 0.06 | J4: 0 | K4: Senado / LC 123
A5: Fee por viagem | B5: 100 | C5: R$/viagem | D5: Input | E5: Premissa não validada | F5: Sprint 4 | H5: 360000 | I5: 0.112 | J5: 9360 | K5: Senado / LC 123
A6: Taxa processamento fee | B6: 0.03 | C6: % fee | D6: Input | E6: Premissa gerencial v1 | F6: Hipótese Antévia | H6: 720000 | I6: 0.135 | J6: 17640 | K6: Senado / LC 123
A7: Perdas operacionais | B7: 0.01 | C7: % receita | D7: Input | E7: Premissa gerencial v1 | F7: Hipótese Antévia | H7: 1800000 | I7: 0.16 | J7: 35640 | K7: Senado / LC 123
A8: Reserva mínima A | B8: 16500 | C8: R$ | D8: Input | E8: 3 meses OPEX médio A1 | F8: Cálculo Antévia | H8: 3600000 | I8: 0.21 | J8: 125640 | K8: Senado / LC 123
A9: Reserva mínima B | B9: 53700 | C9: R$ | D9: Input | E9: 3 meses OPEX médio B1 | F9: Cálculo Antévia | H9: 4800000 | I9: 0.329 | J9: 648000 | K9: Senado / LC 123
A10: CAPEX A1 | B10: 8000 | C10: R$ | D10: Input | E10: Equipamentos | F10: Hipótese Antévia
A11: CAPEX A2 | B11: 24000 | C11: R$ | D11: Input | E11: Equipamentos + tecnologia | F11: Hipótese Antévia | H11: Fontes externas
A12: CAPEX A3 | B12: 48000 | C12: R$ | D12: Input | E12: Equipamentos + tecnologia | F12: Hipótese Antévia | H12: Simples 2027 / RTC | I12: https://www.gov.br/receitafederal/pt-br/assuntos/noticias/2026/agosto/cgsn-atualiza-regras-do-simples-nacional-para-adequacao-a-reforma-tributaria-do-consumo
A13: OPEX A1 | B13: 66000 | C13: R$/ano | D13: Input | E13: Founder-led | F13: Hipótese Antévia | H13: LC 214 — Agências de turismo | I13: https://planalto.gov.br/ccivil_03/leis/lcp/lcp214compilado.htm
A14: OPEX A2 | B14: 198800 | C14: R$/ano | D14: Input | E14: 1 FTE Ops/CS + founders | F14: Hipótese Antévia | H14: Anexo III 2027–2028 | I14: https://legis.senado.gov.br/norma/40180341/publicacao/40181117
A15: OPEX A3 | B15: 381600 | C15: R$/ano | D15: Input | E15: 2 FTE Ops/CS; comercial condicional excluído | F15: Hipótese Antévia
A16: OPEX B1 | B16: 214800 | C16: R$/ano | D16: Input | E16: 2 FTEs profissionais | F16: Hipótese Antévia
A17: OPEX B2 | B17: 324000 | C17: R$/ano | D17: Input | E17: Estrutura profissional v1 | F17: Hipótese Antévia
A18: OPEX B3 | B18: 477600 | C18: R$/ano | D18: Input | E18: 2 Ops/CS + comercial | F18: Hipótese Antévia
A19: Sweat equity A1 | B19: 148800 | C19: R$ | D19: Analítico | E19: Fora da DFC | F19: Cálculo Antévia
A20: Tributação-base | B20: Simples Nacional - Anexo III | C20: texto | D20: Input | E20: Enquadramento deve ser validado por contador | F20: LC 123 / alterações 2026
A21: Nota tributária: modelo usa Simples Nacional como base acadêmica. O enquadramento CNAE/Anexo e a opção de IBS/CBS devem ser validados antes da implementação.

Sheet Receita
A1: ANTÉVIA — Receita Tendencial Trimestral
A3: R$ mil | B3: T1 | C3: T2 | D3: T3 | E3: T4 | F3: T5 | G3: T6 | H3: T7 | I3: T8 | J3: T9 | K3: T10 | L3: T11 | M3: T12
A4: Receita tendencial | B4: 7.1 | C4: 14.2 | D4: 21.3 | E4: 28.4 | F4: 56.8 | G4: 65.3 | H4: 76.7 | I4: 85.2 | J4: 148.8 | K4: 171.1 | L4: 200.9 | M4: 223.2
A6: Ano | B6: Receita (R$ mil) | C6: Status | D6: Observação
A7: Ano 1 | B7: 71 | C7: Herdado | D7: Sprint 4
A8: Ano 2 | B8: 284 | C8: Herdado | D8: Sprint 4
A9: Ano 3 | B9: 744 | C9: Herdado | D9: Sprint 4
A11: A distribuição T1–T12 é uma premissa de trimestralização que preserva exatamente os totais anuais do Sprint 4; substituir pelos valores originais se disponibilizados.

Sheet DFC_A
A1: ANTÉVIA — DFC A (R$ mil)
A3: Linha | B3: T1 | C3: T2 | D3: T3 | E3: T4 | F3: T5 | G3: T6 | H3: T7 | I3: T8 | J3: T9 | K3: T10 | L3: T11 | M3: T12
A4: Receita operacional | B4: =Receita_v2!B30/1000 -> 7.1797753 | C4: =Receita_v2!C30/1000 -> 14.160112 | D4: =Receita_v2!D30/1000 -> 21.339888 | E4: =Receita_v2!E30/1000 -> 28.320225 | F4: =Receita_v2!F30/1000 -> 56.640449 | G4: =Receita_v2!G30/1000 -> 65.216292 | H4: =Receita_v2!H30/1000 -> 76.783708 | I4: =Receita_v2!I30/1000 -> 85.359551 | ... M4: =Receita_v2!M30/1000 -> 223.12017
A5: Taxas transacionais | B5: =-Receita_v2!B27*Premissas!$B$6/1000 -> -0.108 | C5: =-Receita_v2!C27*Premissas!$B$6/1000 -> -0.213 | D5: =-Receita_v2!D27*Premissas!$B$6/1000 -> -0.321 | E5: =-Receita_v2!E27*Premissas!$B$6/1000 -> -0.426 | F5: =-Receita_v2!F27*Premissas!$B$6/1000 -> -0.852 | G5: =-Receita_v2!G27*Premissas!$B$6/1000 -> -0.981 | H5: =-Receita_v2!H27*Premissas!$B$6/1000 -> -1.155 | I5: =-Receita_v2!I27*Premissas!$B$6/1000 -> -1.284 | ... M5: =-Receita_v2!M27*Premissas!$B$6/1000 -> -3.354
A6: Perdas operacionais | B6: =-B4*Premissas!$B$7 -> -0.071797753 | C6: =-C4*Premissas!$B$7 -> -0.14160112 | D6: =-D4*Premissas!$B$7 -> -0.21339888 | E6: =-E4*Premissas!$B$7 -> -0.28320225 | F6: =-F4*Premissas!$B$7 -> -0.56640449 | G6: =-G4*Premissas!$B$7 -> -0.65216292 | H6: =-H4*Premissas!$B$7 -> -0.76783708 | I6: =-I4*Premissas!$B$7 -> -0.85359551 | ... M6: =-M4*Premissas!$B$7 -> -2.2312017
A7: OPEX | B7: =-Premissas!$B$13/4/1000 -> -16.5 | C7: =-Premissas!$B$13/4/1000 -> -16.5 | D7: =-Premissas!$B$13/4/1000 -> -16.5 | E7: =-Premissas!$B$13/4/1000 -> -16.5 | F7: =-Premissas!$B$14/4/1000 -> -49.7 | G7: =-Premissas!$B$14/4/1000 -> -49.7 | H7: =-Premissas!$B$14/4/1000 -> -49.7 | I7: =-Premissas!$B$14/4/1000 -> -49.7 | J7: =-Premissas!$B$15/4/1000 -> -95.4 | K7: =-Premissas!$B$15/4/1000 -> -95.4 | L7: =-Premissas!$B$15/4/1000 -> -95.4 | M7: =-Premissas!$B$15/4/1000 -> -95.4
A8: Tributos (provisão modelada) | B8: =-Tributacao_v3!B9/1000 -> -0.43078652 | C8: =-Tributacao_v3!C9/1000 -> -0.84960674 | D8: =-Tributacao_v3!D9/1000 -> -1.2803933 | E8: =-Tributacao_v3!E9/1000 -> -1.6992135 | F8: =-Tributacao_v3!F9/1000 -> -3.398427 | G8: =-Tributacao_v3!G9/1000 -> -3.9129775 | H8: =-Tributacao_v3!H9/1000 -> -5.4331672 | I8: =-Tributacao_v3!I9/1000 -> -6.7470112 | ... M8: =-Tributacao_v3!M9/1000 -> -25.011052
A9: Fluxo operacional | B9: =SUM(B4:B8) -> -9.930809 | C9: =SUM(C4:C8) -> -3.5440955 | D9: =SUM(D4:D8) -> 3.0250955 | E9: =SUM(E4:E8) -> 9.411809 | F9: =SUM(F4:F8) -> 2.123618 | G9: =SUM(G4:G8) -> 9.9701517 | H9: =SUM(H4:H8) -> 19.727704 | I9: =SUM(I4:I8) -> 26.774944 | ... M9: =SUM(M4:M8) -> 97.123918
A10: CAPEX | B10: =-Premissas!$B$10/1000 -> -8 | C10: 0 | D10: 0 | E10: 0 | F10: =-Premissas!$B$11/1000 -> -24 | G10: 0 | H10: 0 | I10: 0 | J10: =-Premissas!$B$12/1000 -> -48 | K10: 0 | L10: 0 | M10: 0
A11: FCL pré-funding | B11: =SUM(B9:B10) -> -17.930809 | C11: =SUM(C9:C10) -> -3.5440955 | D11: =SUM(D9:D10) -> 3.0250955 | E11: =SUM(E9:E10) -> 9.411809 | F11: =SUM(F9:F10) -> -21.876382 | G11: =SUM(G9:G10) -> 9.9701517 | H11: =SUM(H9:H10) -> 19.727704 | I11: =SUM(I9:I10) -> 26.774944 | ... M11: =SUM(M9:M10) -> 97.123918
A12: Funding inicial | B12: =-MIN(0,MIN(B17:M17))+Premissas!$B$8/1000 -> 47.414382 | C12: 0 | D12: 0 | E12: 0 | F12: 0 | G12: 0 | H12: 0 | I12: 0 | J12: 0 | K12: 0 | L12: 0 | M12: 0
A13: Variação líquida de caixa | B13: =B11+B12 -> 29.483573 | C13: =C11+C12 -> -3.5440955 | D13: =D11+D12 -> 3.0250955 | E13: =E11+E12 -> 9.411809 | F13: =F11+F12 -> -21.876382 | G13: =G11+G12 -> 9.9701517 | H13: =H11+H12 -> 19.727704 | I13: =I11+I12 -> 26.774944 | ... M13: =M11+M12 -> 97.123918
A14: Caixa acumulado | B14: =B13 -> 29.483573 | C14: =B14+C13 -> 25.939478 | D14: =C14+D13 -> 28.964573 | E14: =D14+E13 -> 38.376382 | F14: =E14+F13 -> 16.5 | G14: =F14+G13 -> 26.470152 | H14: =G14+H13 -> 46.197855 | I14: =H14+I13 -> 72.972799 | J14: =I14+J13 -> 61.60729 | ... M14: =L14+M13 -> 292.50549
A17: Cumulativo pré-funding | B17: =B11 -> -17.930809 | C17: =B17+C11 -> -21.474904 | D17: =C17+D11 -> -18.449809 | E17: =D17+E11 -> -9.038 | F17: =E17+F11 -> -30.914382 | G17: =F17+G11 -> -20.94423 | H17: =G17+H11 -> -1.2165267 | I17: =H17+I11 -> 25.558417 | J17: =I17+J11 -> 14.192908 | ... M17: =L17+M11 -> 245.0911
A19: Tributos v3: vinculados à aba Tributacao_v3, usando Anexo III e alíquota efetiva por RBT12 aproximada trimestralmente. A apuração legal é mensal; o modelo serve à projeção econômico-financeira do E6.
A21: Receita agora vinculada à Receita_v2 bottom-up. O modelo reconcilia as receitas herdadas via drivers explícitos; fee/comissão continuam premissas a validar no MVP.

Sheet DFC_B
A1: ANTÉVIA — DFC B (R$ mil)
A3: Linha | B3: T1 | C3: T2 | D3: T3 | E3: T4 | F3: T5 | G3: T6 | H3: T7 | I3: T8 | J3: T9 | K3: T10 | L3: T11 | M3: T12
A4: Receita operacional | B4: =Receita_v2!B30/1000 -> 7.1797753 | C4: =Receita_v2!C30/1000 -> 14.160112 | D4: =Receita_v2!D30/1000 -> 21.339888 | E4: =Receita_v2!E30/1000 -> 28.320225 | F4: =Receita_v2!F30/1000 -> 56.640449 | G4: =Receita_v2!G30/1000 -> 65.216292 | H4: =Receita_v2!H30/1000 -> 76.783708 | I4: =Receita_v2!I30/1000 -> 85.359551 | ... M4: =Receita_v2!M30/1000 -> 223.12017
A5: Taxas transacionais | B5: =-Receita_v2!B27*Premissas!$B$6/1000 -> -0.108 | C5: =-Receita_v2!C27*Premissas!$B$6/1000 -> -0.213 | D5: =-Receita_v2!D27*Premissas!$B$6/1000 -> -0.321 | E5: =-Receita_v2!E27*Premissas!$B$6/1000 -> -0.426 | F5: =-Receita_v2!F27*Premissas!$B$6/1000 -> -0.852 | G5: =-Receita_v2!G27*Premissas!$B$6/1000 -> -0.981 | H5: =-Receita_v2!H27*Premissas!$B$6/1000 -> -1.155 | I5: =-Receita_v2!I27*Premissas!$B$6/1000 -> -1.284 | ... M5: =-Receita_v2!M27*Premissas!$B$6/1000 -> -3.354
A6: Perdas operacionais | B6: =-B4*Premissas!$B$7 -> -0.071797753 | C6: =-C4*Premissas!$B$7 -> -0.14160112 | D6: =-D4*Premissas!$B$7 -> -0.21339888 | E6: =-E4*Premissas!$B$7 -> -0.28320225 | F6: =-F4*Premissas!$B$7 -> -0.56640449 | G6: =-G4*Premissas!$B$7 -> -0.65216292 | H6: =-H4*Premissas!$B$7 -> -0.76783708 | I6: =-I4*Premissas!$B$7 -> -0.85359551 | ... M6: =-M4*Premissas!$B$7 -> -2.2312017
A7: OPEX | B7: =-Premissas!$B$16/4/1000 -> -53.7 | C7: =-Premissas!$B$16/4/1000 -> -53.7 | D7: =-Premissas!$B$16/4/1000 -> -53.7 | E7: =-Premissas!$B$16/4/1000 -> -53.7 | F7: =-Premissas!$B$17/4/1000 -> -81 | G7: =-Premissas!$B$17/4/1000 -> -81 | H7: =-Premissas!$B$17/4/1000 -> -81 | I7: =-Premissas!$B$17/4/1000 -> -81 | J7: =-Premissas!$B$18/4/1000 -> -119.4 | K7: =-Premissas!$B$18/4/1000 -> -119.4 | L7: =-Premissas!$B$18/4/1000 -> -119.4 | M7: =-Premissas!$B$18/4/1000 -> -119.4
A8: Tributos (provisão modelada) | B8: =-Tributacao_v3!B9/1000 -> -0.43078652 | C8: =-Tributacao_v3!C9/1000 -> -0.84960674 | D8: =-Tributacao_v3!D9/1000 -> -1.2803933 | E8: =-Tributacao_v3!E9/1000 -> -1.6992135 | F8: =-Tributacao_v3!F9/1000 -> -3.398427 | G8: =-Tributacao_v3!G9/1000 -> -3.9129775 | H8: =-Tributacao_v3!H9/1000 -> -5.4331672 | I8: =-Tributacao_v3!I9/1000 -> -6.7470112 | ... M8: =-Tributacao_v3!M9/1000 -> -25.011052
A9: Fluxo operacional | B9: =SUM(B4:B8) -> -47.130809 | C9: =SUM(C4:C8) -> -40.744096 | D9: =SUM(D4:D8) -> -34.174904 | E9: =SUM(E4:E8) -> -27.788191 | F9: =SUM(F4:F8) -> -29.176382 | G9: =SUM(G4:G8) -> -21.329848 | H9: =SUM(H4:H8) -> -11.572296 | I9: =SUM(I4:I8) -> -4.5250562 | ... M9: =SUM(M4:M8) -> 73.123918
A10: CAPEX | B10: =-Premissas!$B$10/1000 -> -8 | C10: 0 | D10: 0 | E10: 0 | F10: =-Premissas!$B$11/1000 -> -24 | G10: 0 | H10: 0 | I10: 0 | J10: =-Premissas!$B$12/1000 -> -48 | K10: 0 | L10: 0 | M10: 0
A11: FCL pré-funding | B11: =SUM(B9:B10) -> -55.130809 | C11: =SUM(C9:C10) -> -40.744096 | D11: =SUM(D9:D10) -> -34.174904 | E11: =SUM(E9:E10) -> -27.788191 | F11: =SUM(F9:F10) -> -53.176382 | G11: =SUM(G9:G10) -> -21.329848 | H11: =SUM(H9:H10) -> -11.572296 | I11: =SUM(I9:I10) -> -4.5250562 | ... M11: =SUM(M9:M10) -> 73.123918
A12: Funding inicial | B12: =-MIN(0,MIN(B17:M17))+Premissas!$B$9/1000 -> 337.50709 | C12: 0 | D12: 0 | E12: 0 | F12: 0 | G12: 0 | H12: 0 | I12: 0 | J12: 0 | K12: 0 | L12: 0 | M12: 0
A13: Variação líquida de caixa | B13: =B11+B12 -> 282.37628 | C13: =C11+C12 -> -40.744096 | D13: =D11+D12 -> -34.174904 | E13: =E11+E12 -> -27.788191 | F13: =F11+F12 -> -53.176382 | G13: =G11+G12 -> -21.329848 | H13: =H11+H12 -> -11.572296 | I13: =I11+I12 -> -4.5250562 | ... M13: =M11+M12 -> 73.123918
A14: Caixa acumulado | B14: =B13 -> 282.37628 | C14: =B14+C13 -> 241.63219 | D14: =C14+D13 -> 207.45728 | E14: =D14+E13 -> 179.66909 | F14: =E14+F13 -> 126.49271 | G14: =F14+G13 -> 105.16286 | H14: =G14+H13 -> 93.590566 | I14: =H14+I13 -> 89.065509 | J14: =I14+J13 -> 53.7 | ... M14: =L14+M13 -> 212.5982
A17: Cumulativo pré-funding | B17: =B11 -> -55.130809 | C17: =B17+C11 -> -95.874904 | D17: =C17+D11 -> -130.04981 | E17: =D17+E11 -> -157.838 | F17: =E17+F11 -> -211.01438 | G17: =F17+G11 -> -232.34423 | H17: =G17+H11 -> -243.91653 | I17: =H17+I11 -> -248.44158 | J17: =I17+J11 -> -283.80709 | ... M17: =L17+M11 -> -124.9089
A19: Tributos v3: vinculados à aba Tributacao_v3, usando Anexo III e alíquota efetiva por RBT12 aproximada trimestralmente. A apuração legal é mensal; o modelo serve à projeção econômico-financeira do E6.
A21: Receita agora vinculada à Receita_v2 bottom-up. O modelo reconcilia as receitas herdadas via drivers explícitos; fee/comissão continuam premissas a validar no MVP.

Sheet Resumo
A1: ANTÉVIA — Resumo A × B
A3: Indicador | B3: A — Bootstrap | C3: B — Angel | E3: Valuation pre-money (R$ mil) | F3: Aporte B (R$ mil) | G3: Post-money | H3: Diluição
A4: Funding inicial (R$ mil) | B4: =DFC_A!B12 -> 47.414382 | C4: =DFC_B!B12 -> 337.50709 | E4: 1000 | F4: =DFC_B!B12 -> 337.50709 | G4: =E4+F4 -> 1337.5071 | H4: =F4/G4 -> 0.25234041
A5: Caixa final T12 (R$ mil) | B5: =DFC_A!M14 -> 292.50549 | C5: =DFC_B!M14 -> 212.5982 | E5: 1500 | F5: =DFC_B!B12 -> 337.50709 | G5: =E5+F5 -> 1837.5071 | H5: =F5/G5 -> 0.18367662
A6: FCL pré-funding 3 anos (R$ mil) | B6: =SUM(DFC_A!B11:M11) -> 245.0911 | C6: =SUM(DFC_B!B11:M11) -> -124.9089 | E6: 2000 | F6: =DFC_B!B12 -> 337.50709 | G6: =E6+F6 -> 2337.5071 | H6: =F6/G6 -> 0.14438762
A7: Sweat equity A1 (R$ mil) | B7: =Premissas!B19/1000 -> 148.8 | C7: 0
A8: Staff profissional A1 | B8: Founder-led | C8: 2 FTEs
A9: Dívida | B9: Não | C9: Não
A10: Diluição | B10: Não | C10: Sim
A12: Caixa acumulado | B12: T1 | C12: T2 | D12: T3 | E12: T4 | F12: T5 | G12: T6 | H12: T7 | I12: T8 | J12: T9 | K12: T10 | L12: T11 | M12: T12
A13: A | B13: =DFC_A!B14 -> 29.483573 | C13: =DFC_A!C14 -> 25.939478 | D13: =DFC_A!D14 -> 28.964573 | E13: =DFC_A!E14 -> 38.376382 | F13: =DFC_A!F14 -> 16.5 | G13: =DFC_A!G14 -> 26.470152 | H13: =DFC_A!H14 -> 46.197855 | I13: =DFC_A!I14 -> 72.972799 | ... M13: =DFC_A!M14 -> 292.50549
A14: B | B14: =DFC_B!B14 -> 282.37628 | C14: =DFC_B!C14 -> 241.63219 | D14: =DFC_B!D14 -> 207.45728 | E14: =DFC_B!E14 -> 179.66909 | F14: =DFC_B!F14 -> 126.49271 | G14: =DFC_B!G14 -> 105.16286 | H14: =DFC_B!H14 -> 93.590566 | I14: =DFC_B!I14 -> 89.065509 | ... M14: =DFC_B!M14 -> 212.5982
A16: Tributação v3 | B16: A — Bootstrap | C16: B — Angel
A17: DAS Ano 1 (R$ mil) | B17: =Tributacao_v3!C13/1000 -> 4.26 | C17: =Tributacao_v3!C13/1000 -> 4.26
A18: DAS Ano 2 (R$ mil) | B18: =Tributacao_v3!C14/1000 -> 19.491583 | C18: =Tributacao_v3!C14/1000 -> 19.491583
A19: DAS Ano 3 (R$ mil) | B19: =Tributacao_v3!C15/1000 -> 76.243312 | C19: =Tributacao_v3!C15/1000 -> 76.243312
A20: Carga efetiva A3 | B20: =Tributacao_v3!D15 -> 0.10247757 | C20: =Tributacao_v3!D15 -> 0.10247757

Sheet Sensibilidade
A1: Sensibilidades prioritárias — Antévia
A3: Variável | B3: Pessimista | C3: Tendencial | D3: Otimista | E3: Impacto esperado | F3: Status
A4: Fee (R$) | B4: 50 | C4: 100 | D4: 150 | E4: Receita / margem | F4: Sprint 4
A5: Tempo humano/viagem (min) | B5: 30 | C5: 20 | D5: 15 | E5: Headcount / OPEX | F5: Premissa
A6: Perdas operacionais | B6: 0.02 | C6: 0.01 | D6: 0.005 | E6: FCL | F6: Premissa
A7: Touchless rate | B7: 0.6 | C7: 0.8 | D7: 0.9 | E7: Capacidade operacional | F7: Premissa

Sheet Receita_v2
A1: ANTÉVIA — Receita v2 Bottom-up e Reconciliação
A3: Driver | B3: Ano 1 | C3: Ano 2 | D3: Ano 3 | E3: Unidade | F3: Natureza | G3: Observação | H3: Fonte/Status | I3: Fórmula-chave | J3: Validação | O3: Controle | P3: Resultado | Q3: Status
A4: Escolas parceiras | B4: 2 | C4: 5 | D4: 10 | E4: escolas | F4: Input E6 | G4: Ramp-up comercial | H4: Premissa E6 | I4: driver | O4: Viagens 3 anos | P4: =SUM(B23:M23) -> 5508 | Q4: =IF(P4=5508,"OK","REVER") -> OK
A5: Alunos elegíveis / escola | B5: 100 | C5: 100 | D5: 100 | E5: alunos | F5: Input E6 | G5: Base endereçável por escola | H5: Premissa E6 | I5: driver | O5: Receita A1 | P5: =SUM(B30:E30) -> 71000 | Q5: =IF(ABS(P5-B17)<1,"OK","REVER") -> OK
A6: Taxa de adesão | B6: 0.5 | C6: 0.6 | D6: 0.65 | E6: % | F6: Input E6 | G6: Conversão elegível → ativo | H6: Premissa E6 | I6: driver | O6: Receita A2 | P6: =SUM(F30:I30) -> 284000 | Q6: =IF(ABS(P6-C17)<1,"OK","REVER") -> OK
A7: Alunos ativos | B7: =B4*B5*B6 -> 100 | C7: =C4*C5*C6 -> 300 | D7: =D4*D5*D6 -> 650 | E7: alunos | F7: Cálculo | G7: Escolas × elegíveis × adesão | H7: Calculado | I7: escolas x elegíveis x adesão | O7: Receita A3 | P7: =SUM(J30:M30) -> 744000 | Q7: =IF(ABS(P7-D17)<1,"OK","REVER") -> OK
A8: Viagens monetizadas | B8: 356 | C8: 1424 | D8: 3728 | E8: viagens | F8: Input de reconciliação | G8: Total 3 anos = 5.508 | H8: Referência herdada | I8: referência
A9: Viagens / aluno ativo | B9: =B8/B7 -> 3.56 | C9: =C8/C7 -> 4.7466667 | D9: =D8/D7 -> 5.7353846 | E9: x | F9: Cálculo | G9: Intensidade de uso | H9: Calculado | I9: viagens / alunos ativos
A10: Fee médio | B10: 100 | C10: 100 | D10: 100 | E10: R$/viagem | F10: Input E6 | G10: Ponto médio da hipótese R$50–150 | H10: Projeto / hipótese | I10: premissa | O10: Unit economics | P10: Valor tendencial | Q10: Unidade
A11: Ticket médio GMV | B11: =(B17/B8-B10)/B12 -> 1988.764 | C11: =(C17/C8-C10)/C12 -> 1988.764 | D11: =(D17/D8-D10)/D12 -> 1991.4163 | E11: R$/viagem | F11: Cálculo de reconciliação | G11: Ticket implícito com comissão de 5% | H11: Calculado | I11: receita-alvo / viagens | O11: Fee / viagem | P11: =B10 -> 100 | Q11: R$
A12: Comissão média fornecedor | B12: 0.05 | C12: 0.05 | D12: 0.05 | E12: % GMV | F12: Input E6 | G12: Hipótese de monetização B2B | H12: Premissa E6 | I12: premissa | O12: Ticket GMV / viagem | P12: =AVERAGE(B11:D11) -> 1989.6481 | Q12: R$
A13: Receita fee | B13: =B8*B10 -> 35600 | C13: =C8*C10 -> 142400 | D13: =D8*D10 -> 372800 | E13: R$ | F13: Cálculo | G13: Viagens × fee | H13: Calculado | I13: viagens x fee | O13: Comissão | P13: =B12 -> 0.05 | Q13: % GMV
A14: GMV intermediado | B14: =B8*B11 -> 708000 | C14: =C8*C11 -> 2832000 | D14: =D8*D11 -> 7424000 | E14: R$ | F14: Cálculo | G14: Viagens × ticket médio | H14: Calculado | I14: viagens x ticket | O14: Receita / viagem | P14: =B16/B8 -> 199.4382 | Q14: R$
A15: Receita comissão | B15: =B14*B12 -> 35400 | C15: =C14*C12 -> 141600 | D15: =D14*D12 -> 371200 | E15: R$ | F15: Cálculo | G15: GMV × comissão | H15: Calculado | I15: GMV x comissão | O15: Custo processamento / viagem | P15: =P11*Premissas!B6 -> 3 | Q15: R$
A16: Receita bottom-up | B16: =B13+B15 -> 71000 | C16: =C13+C15 -> 284000 | D16: =D13+D15 -> 744000 | E16: R$ | F16: Cálculo | G16: Fee + comissão | H16: Calculado | I16: fee + comissão | O16: Margem antes OPEX / viagem | P16: =P14-P15-P14*Premissas!B7 -> 194.44382 | Q16: R$
A17: Receita herdada | B17: 71000 | C17: 284000 | D17: 744000 | E17: R$ | F17: Benchmark | G17: Sprint anterior | H17: Referência herdada | I17: benchmark
A18: Gap reconciliação | B18: =B16-B17 -> 0 | C18: =C16-C17 -> 0 | D18: =D16-D17 -> 0 | E18: R$ | F18: Cálculo | G18: Bottom-up – herdada | H18: Calculado | I18: bottom-up - herdada | O18: ATENÇÃO: escolas, base elegível, adesão, fee e comissão são premissas E6. O ticket médio (~R$1,99 mil) é o valor implícito necessário para reconciliar as receitas herdadas com fee de R$100 e comissão de 5%.
A19: Gap % | B19: =B18/B17 -> 0 | C19: =C18/C17 -> 0 | D19: =D18/D17 -> 0 | E19: % | F19: Cálculo | G19: Gap / receita herdada | H19: Calculado | I19: gap / herdada
A22: R$ / viagens | B22: T1 | C22: T2 | D22: T3 | E22: T4 | F22: T5 | G22: T6 | H22: T7 | I22: T8 | J22: T9 | K22: T10 | L22: T11 | M22: T12
A23: Viagens monetizadas | B23: 36 | C23: 71 | D23: 107 | E23: 142 | F23: 284 | G23: 327 | H23: 385 | I23: 428 | J23: 746 | K23: 857 | L23: 1007 | M23: 1118
A24: Fee médio | B24: =B10 -> 100 | C24: =B10 -> 100 | D24: =B10 -> 100 | E24: =B10 -> 100 | F24: =C10 -> 100 | G24: =C10 -> 100 | H24: =C10 -> 100 | I24: =C10 -> 100 | J24: =D10 -> 100 | K24: =D10 -> 100 | L24: =D10 -> 100 | M24: =D10 -> 100
A25: Ticket médio GMV | B25: =B11 -> 1988.764 | C25: =B11 -> 1988.764 | D25: =B11 -> 1988.764 | E25: =B11 -> 1988.764 | F25: =C11 -> 1988.764 | G25: =C11 -> 1988.764 | H25: =C11 -> 1988.764 | I25: =C11 -> 1988.764 | J25: =D11 -> 1991.4163 | K25: =D11 -> 1991.4163 | L25: =D11 -> 1991.4163 | M25: =D11 -> 1991.4163
A26: Comissão média | B26: =B12 -> 0.05 | C26: =B12 -> 0.05 | D26: =B12 -> 0.05 | E26: =B12 -> 0.05 | F26: =C12 -> 0.05 | G26: =C12 -> 0.05 | H26: =C12 -> 0.05 | I26: =C12 -> 0.05 | J26: =D12 -> 0.05 | K26: =D12 -> 0.05 | L26: =D12 -> 0.05 | M26: =D12 -> 0.05
A27: Receita fee | B27: =B23*B24 -> 3600 | C27: =C23*C24 -> 7100 | D27: =D23*D24 -> 10700 | E27: =E23*E24 -> 14200 | F27: =F23*F24 -> 28400 | G27: =G23*G24 -> 32700 | H27: =H23*H24 -> 38500 | I27: =I23*I24 -> 42800 | ... M27: =M23*M24 -> 111800
A28: GMV intermediado | B28: =B23*B25 -> 71595.506 | C28: =C23*C25 -> 141202.25 | D28: =D23*D25 -> 212797.75 | E28: =E23*E25 -> 282404.49 | F28: =F23*F25 -> 564808.99 | G28: =G23*G25 -> 650325.84 | H28: =H23*H25 -> 765674.16 | I28: =I23*I25 -> 851191.01 | ... M28: =M23*M25 -> 2226403.4
A29: Receita comissão | B29: =B28*B26 -> 3579.7753 | C29: =C28*C26 -> 7060.1124 | D29: =D28*D26 -> 10639.888 | E29: =E28*E26 -> 14120.225 | F29: =F28*F26 -> 28240.449 | G29: =G28*G26 -> 32516.292 | H29: =H28*H26 -> 38283.708 | I29: =I28*I26 -> 42559.551 | ... M29: =M28*M26 -> 111320.17
A30: Receita bottom-up | B30: =B27+B29 -> 7179.7753 | C30: =C27+C29 -> 14160.112 | D30: =D27+D29 -> 21339.888 | E30: =E27+E29 -> 28320.225 | F30: =F27+F29 -> 56640.449 | G30: =G27+G29 -> 65216.292 | H30: =H27+H29 -> 76783.708 | I30: =I27+I29 -> 85359.551 | ... M30: =M27+M29 -> 223120.17
A33: Leitura: a reconciliação fecha com fee de R$100 + comissão de 5% sobre GMV e ticket médio implícito de aproximadamente R$1.990 por viagem. Escolas, elegíveis, adesão, fee e comissão são premissas E6; 5.508 viagens e receitas anuais são referências herdadas. O ticket é calculado, não assumido, para testar a consistência econômica da projeção.

Sheet Tributacao_v3
A1: ANTÉVIA — Tributação v3 | Simples Nacional — Anexo III
A3: Linha | B3: T1 | C3: T2 | D3: T3 | E3: T4 | F3: T5 | G3: T6 | H3: T7 | I3: T8 | J3: T9 | K3: T10 | L3: T11 | M3: T12
A4: Receita trimestral (R$) | B4: =Receita_v2!B30 -> 7179.7753 | C4: =Receita_v2!C30 -> 14160.112 | D4: =Receita_v2!D30 -> 21339.888 | E4: =Receita_v2!E30 -> 28320.225 | F4: =Receita_v2!F30 -> 56640.449 | G4: =Receita_v2!G30 -> 65216.292 | H4: =Receita_v2!H30 -> 76783.708 | I4: =Receita_v2!I30 -> 85359.551 | ... M4: =Receita_v2!M30 -> 223120.17
A5: RBT12 de referência (R$) | B5: =SUM(B4:B4)*4/1 -> 28719.101 | C5: =SUM(B4:C4)*4/2 -> 42679.775 | D5: =SUM(B4:D4)*4/3 -> 56906.367 | E5: =SUM(B4:E4)*4/4 -> 71000 | F5: =SUM(C4:F4) -> 120460.67 | G5: =SUM(D4:G4) -> 171516.85 | H5: =SUM(E4:H4) -> 226960.67 | I5: =SUM(F4:I4) -> 284000 | J5: =SUM(G4:J4) -> 376239.38 | K5: =SUM(H4:K4) -> 482055.28 | L5: =SUM(I4:L4) -> 606239.38 | M5: =SUM(J4:M4) -> 744000
A6: Alíquota nominal | B6: =IF(B5<=180000,6%,IF(B5<=360000,11.2%,IF(B5<=720000,13.5%,IF(B5<=1800000,16%,IF(B5<=3600000,21%,32.9%))))) -> 0.06 | C6: =IF(C5<=180000,6%,IF(C5<=360000,11.2%,IF(C5<=720000,13.5%,IF(C5<=1800000,16%,IF(C5<=3600000,21%,32.9%))))) -> 0.06 | D6: =IF(D5<=180000,6%,IF(D5<=360000,11.2%,IF(D5<=720000,13.5%,IF(D5<=1800000,16%,IF(D5<=3600000,21%,32.9%))))) -> 0.06 | E6: =IF(E5<=180000,6%,IF(E5<=360000,11.2%,IF(E5<=720000,13.5%,IF(E5<=1800000,16%,IF(E5<=3600000,21%,32.9%))))) -> 0.06 | F6: =IF(F5<=180000,6%,IF(F5<=360000,11.2%,IF(F5<=720000,13.5%,IF(F5<=1800000,16%,IF(F5<=3600000,21%,32.9%))))) -> 0.06 | G6: =IF(G5<=180000,6%,IF(G5<=360000,11.2%,IF(G5<=720000,13.5%,IF(G5<=1800000,16%,IF(G5<=3600000,21%,32.9%))))) -> 0.06 | H6: =IF(H5<=180000,6%,IF(H5<=360000,11.2%,IF(H5<=720000,13.5%,IF(H5<=1800000,16%,IF(H5<=3600000,21%,32.9%))))) -> 0.112 | I6: =IF(I5<=180000,6%,IF(I5<=360000,11.2%,IF(I5<=720000,13.5%,IF(I5<=1800000,16%,IF(I5<=3600000,21%,32.9%))))) -> 0.112 | ... M6: =IF(M5<=180000,6%,IF(M5<=360000,11.2%,IF(M5<=720000,13.5%,IF(M5<=1800000,16%,IF(M5<=3600000,21%,32.9%))))) -> 0.16
A7: Parcela a deduzir (R$) | B7: =IF(B5<=180000,0,IF(B5<=360000,9360,IF(B5<=720000,17640,IF(B5<=1800000,35640,IF(B5<=3600000,125640,648000))))) -> 0 | C7: =IF(C5<=180000,0,IF(C5<=360000,9360,IF(C5<=720000,17640,IF(C5<=1800000,35640,IF(C5<=3600000,125640,648000))))) -> 0 | D7: =IF(D5<=180000,0,IF(D5<=360000,9360,IF(D5<=720000,17640,IF(D5<=1800000,35640,IF(D5<=3600000,125640,648000))))) -> 0 | E7: =IF(E5<=180000,0,IF(E5<=360000,9360,IF(E5<=720000,17640,IF(E5<=1800000,35640,IF(E5<=3600000,125640,648000))))) -> 0 | F7: =IF(F5<=180000,0,IF(F5<=360000,9360,IF(F5<=720000,17640,IF(F5<=1800000,35640,IF(F5<=3600000,125640,648000))))) -> 0 | G7: =IF(G5<=180000,0,IF(G5<=360000,9360,IF(G5<=720000,17640,IF(G5<=1800000,35640,IF(G5<=3600000,125640,648000))))) -> 0 | H7: =IF(H5<=180000,0,IF(H5<=360000,9360,IF(H5<=720000,17640,IF(H5<=1800000,35640,IF(H5<=3600000,125640,648000))))) -> 9360 | I7: =IF(I5<=180000,0,IF(I5<=360000,9360,IF(I5<=720000,17640,IF(I5<=1800000,35640,IF(I5<=3600000,125640,648000))))) -> 9360 | ... M7: =IF(M5<=180000,0,IF(M5<=360000,9360,IF(M5<=720000,17640,IF(M5<=1800000,35640,IF(M5<=3600000,125640,648000))))) -> 35640
A8: Alíquota efetiva | B8: =(B5*B6-B7)/B5 -> 0.06 | C8: =(C5*C6-C7)/C5 -> 0.06 | D8: =(D5*D6-D7)/D5 -> 0.06 | E8: =(E5*E6-E7)/E5 -> 0.06 | F8: =(F5*F6-F7)/F5 -> 0.06 | G8: =(G5*G6-G7)/G5 -> 0.06 | H8: =(H5*H6-H7)/H5 -> 0.070759375 | I8: =(I5*I6-I7)/I5 -> 0.079042254 | ... M8: =(M5*M6-M7)/M5 -> 0.11209677
A9: DAS estimado trimestre (R$) | B9: =B4*B8 -> 430.78652 | C9: =C4*C8 -> 849.60674 | D9: =D4*D8 -> 1280.3933 | E9: =E4*E8 -> 1699.2135 | F9: =F4*F8 -> 3398.427 | G9: =G4*G8 -> 3912.9775 | H9: =H4*H8 -> 5433.1672 | I9: =I4*I8 -> 6747.0112 | ... M9: =M4*M8 -> 25011.052
A12: Ano | B12: Receita | C12: DAS estimado | D12: Alíquota efetiva média | E12: Observação
A13: Ano 1 | B13: =SUM(B4:E4) -> 71000 | C13: =SUM(B9:E9) -> 4260 | D13: =C13/B13 -> 0.06 | E13: Anexo III — proxy trimestral RBT12
A14: Ano 2 | B14: =SUM(F4:I4) -> 284000 | C14: =SUM(F9:I9) -> 19491.583 | D14: =C14/B14 -> 0.068632334 | E14: Anexo III — proxy trimestral RBT12
A15: Ano 3 | B15: =SUM(J4:M4) -> 744000 | C15: =SUM(J9:M9) -> 76243.312 | D15: =C15/B15 -> 0.10247757 | E15: Anexo III — proxy trimestral RBT12
A18: Premissa-base E6: agência de viagem/turismo no Simples Nacional, Anexo III, sem Fator R. A apuração acima é uma aproximação trimestral para projeção acadêmica: a obrigação real é mensal e deve considerar a RBT12 e regras de início de atividade do PGDAS-D. A partir de 2027 IBS/CBS integram o Simples; a empresa pode optar pelo recolhimento regular desses tributos. A LC 214/2025 prevê regime específico para intermediação turística, deduzindo da base de IBS/CBS os valores repassados aos fornecedores intermediados e incluindo comissões/incentivos.
A23: Fonte | B23: Referência | C23: Uso no modelo
A24: Receita Federal — Perguntão Simples | B24: Agência de viagem e turismo: Anexo III, sem Fator R | C24: Enquadramento-base
A25: LC 123 — Anexo III 2027–2028 | B25: Faixas 6%; 11,2%; 13,5%; 16%; 21%; 32,9% | C25: Cálculo da alíquota efetiva
A26: LC 214/2025, art. 289 | B26: Regime específico de intermediação turística | C26: Base IBS/CBS
A27: Receita Federal — Res. CGSN 190/191 | B27: IBS/CBS incorporados ao Simples a partir de 2027 | C27: Reforma tributária
A28: Receita Federal — regime de caixa | B28: Apuração mensal passa a reconhecer receita por faturamento | C28: Capital de giro / ressalva

Sheet Stress_Test
A1: ANTÉVIA — Stress Test A × B | Pessimista • Tendencial • Otimista
A3: Driver | B3: Pessimista | C3: Tendencial | D3: Otimista | E3: Unidade | F3: Interpretação | G3: Status | I3: Cenário | J3: Funding A | K3: Caixa final A | L3: Funding B | M3: Caixa final B | N3: Receita 3a | O3: FCL A | P3: FCL B | Q3: Status
A4: Volume de viagens vs. base | B4: 0.7 | C4: 1 | D4: 1.2 | E4: x | F4: Adesão/uso agregado | G4: Premissa E6 | I4: Pessimista | J4: =E12 -> 356.11498 | K4: =M25+E12 -> 18.15 | L4: =F12 -> 804.03498 | M4: =M26+F12 -> 59.07 | N4: =SUM(B12:D12)/1000 -> 519.3929 | O4: =SUM(B23:M23) -> -337.96498 | P4: =SUM(B24:M24) -> -744.96498 | Q4: =IF(M4>0,"Sobrevive","Rever") -> Sobrevive
A5: Fee vs. base | B5: 0.75 | C5: 1 | D5: 1.25 | E5: x | F5: R$75 / R$100 / R$125 | G5: Premissa E6 | I5: Tendencial | J5: =E13 -> 47.757151 | K5: =M30+E13 -> 292.85429 | L5: =F13 -> 339.71036 | M5: =M31+F13 -> 214.80749 | N5: =SUM(B13:D13)/1000 -> 1099 | O5: =SUM(B28:M28) -> 245.09713 | P5: =SUM(B29:M29) -> -124.90287 | Q5: =IF(M5>0,"Sobrevive","Rever") -> Sobrevive
A6: Comissão vs. base | B6: 0.6 | C6: 1 | D6: 1.2 | E6: x | F6: 3% / 5% / 6% do GMV | G6: Premissa E6 | I6: Otimista | J6: =E14 -> 29.751076 | K6: =M35+E14 -> 771.41359 | L6: =F14 -> 191.96517 | M6: =M36+F14 -> 582.12768 | N6: =SUM(B14:D14)/1000 -> 1615.5959 | O6: =SUM(B33:M33) -> 741.66251 | P6: =SUM(B34:M34) -> 390.16251 | Q6: =IF(M6>0,"Sobrevive","Rever") -> Sobrevive
A7: OPEX vs. base | B7: 1.1 | C7: 1 | D7: 0.95 | E7: x | F7: Pressão/eficiência de custos | G7: Premissa E6
A8: Perdas operacionais | B8: 0.02 | C8: 0.01 | D8: 0.005 | E8: % receita | F8: Chargebacks/compensações | G8: Premissa E6
I9: Cenário | J9: Funding A | K9: Funding B | L9: Receita 3 anos
I10: Pessimista | J10: =J4 -> 356.11498 | K10: =L4 -> 804.03498 | L10: =N4 -> 519.3929
A11: Cenário | B11: Receita A1 | C11: Receita A2 | D11: Receita A3 | E11: Funding A | F11: Funding B | G11: Leitura | I11: Tendencial | J11: =J5 -> 47.757151 | K11: =L5 -> 339.71036 | L11: =N5 -> 1099
A12: Pessimista | B12: =71000*$B$4*(0.501*$B$5+0.499*$B$6) -> 33554.955 | C12: =284000*$B$4*(0.501*$B$5+0.499*$B$6) -> 134219.82 | D12: =744000*$B$4*(0.501*$B$5+0.499*$B$6) -> 351618.12 | E12: =-MIN(0,MIN(B25:M25))+16.5*$B$7 -> 356.11498 | F12: =-MIN(0,MIN(B26:M26))+53.7*$B$7 -> 804.03498 | G12: =IF(F12>500,"Capital intensivo","Dentro da faixa analisável") -> Capital intensivo | I12: Otimista | J12: =J6 -> 29.751076 | K12: =L6 -> 191.96517 | L12: =N6 -> 1615.5959
A13: Tendencial | B13: =71000*$C$4*(0.501*$C$5+0.499*$C$6) -> 71000 | C13: =284000*$C$4*(0.501*$C$5+0.499*$C$6) -> 284000 | D13: =744000*$C$4*(0.501*$C$5+0.499*$C$6) -> 744000 | E13: =-MIN(0,MIN(B30:M30))+16.5*$C$7 -> 47.757151 | F13: =-MIN(0,MIN(B31:M31))+53.7*$C$7 -> 339.71036 | G13: =IF(F13>500,"Capital intensivo","Dentro da faixa analisável") -> Dentro da faixa analisável
A14: Otimista | B14: =71000*$D$4*(0.501*$D$5+0.499*$D$6) -> 104374.26 | C14: =284000*$D$4*(0.501*$D$5+0.499*$D$6) -> 417497.04 | D14: =744000*$D$4*(0.501*$D$5+0.499*$D$6) -> 1093724.6 | E14: =-MIN(0,MIN(B35:M35))+16.5*$D$7 -> 29.751076 | F14: =-MIN(0,MIN(B36:M36))+53.7*$D$7 -> 191.96517 | G14: =IF(F14>500,"Capital intensivo","Dentro da faixa analisável") -> Dentro da faixa analisável
A17: Stress test gerencial: os choques são aplicados aos drivers econômicos, preservando a estrutura A/B. A tributação usa as cargas efetivas médias da v3 como aproximação; para decisão real, cada cenário deve ser recalculado mensalmente no PGDAS-D. O objetivo aqui é testar robustez, não produzir apuração fiscal.
A22: Pessimista | B22: T1 | C22: T2 | D22: T3 | E22: T4 | F22: T5 | G22: T6 | H22: T7 | I22: T8 | J22: T9 | K22: T10 | L22: T11 | M22: T12
A23: FCL A | B23: =(B12*0.1-(B12*0.1*0.501*$B$5/(0.501*$B$5+0.499*$B$6)*3%)-(B12*0.1*$B$8)-(B12*0.1*0.06)-(66000/4*$B$7)-8000)/1000 -> -23.118968 | C23: =(B12*0.2-(B12*0.2*0.501*$B$5/(0.501*$B$5+0.499*$B$6)*3%)-(B12*0.2*$B$8)-(B12*0.2*0.06)-(66000/4*$B$7)-0)/1000 -> -12.087937 | D23: =(B12*0.3-(B12*0.3*0.501*$B$5/(0.501*$B$5+0.499*$B$6)*3%)-(B12*0.3*$B$8)-(B12*0.3*0.06)-(66000/4*$B$7)-0)/1000 -> -9.0569054 | E23: =(B12*0.4-(B12*0.4*0.501*$B$5/(0.501*$B$5+0.499*$B$6)*3%)-(B12*0.4*$B$8)-(B12*0.4*0.06)-(66000/4*$B$7)-0)/1000 -> -6.0258739 | F23: =(C12*0.2-(C12*0.2*0.501*$B$5/(0.501*$B$5+0.499*$B$6)*3%)-(C12*0.2*$B$8)-(C12*0.2*0.0686323342495684)-(198800/4*$B$7)-24000)/1000 -> -54.653474 | G23: =(C12*0.23-(C12*0.23*0.501*$B$5/(0.501*$B$5+0.499*$B$6)*3%)-(C12*0.23*$B$8)-(C12*0.23*0.0686323342495684)-(198800/4*$B$7)-0)/1000 -> -27.050995 | H23: =(C12*0.27-(C12*0.27*0.501*$B$5/(0.501*$B$5+0.499*$B$6)*3%)-(C12*0.27*$B$8)-(C12*0.27*0.0686323342495684)-(198800/4*$B$7)-0)/1000 -> -22.24769 | I23: =(C12*0.3-(C12*0.3*0.501*$B$5/(0.501*$B$5+0.499*$B$6)*3%)-(C12*0.3*$B$8)-(C12*0.3*0.0686323342495684)-(198800/4*$B$7)-0)/1000 -> -18.645211 | J23: =(D12*0.2-(D12*0.2*0.501*$B$5/(0.501*$B$5+0.499*$B$6)*3%)-(D12*0.2*$B$8)-(D12*0.2*0.102477570147266)-(381600/4*$B$7)-48000)/1000 -> -92.403586 | K23: =(D12*0.23-(D12*0.23*0.501*$B$5/(0.501*$B$5+0.499*$B$6)*3%)-(D12*0.23*$B$8)-(D12*0.23*0.102477570147266)-(381600/4*$B$7)-0)/1000 -> -35.323124 | L23: =(D12*0.27-(D12*0.27*0.501*$B$5/(0.501*$B$5+0.499*$B$6)*3%)-(D12*0.27*$B$8)-(D12*0.27*0.102477570147266)-(381600/4*$B$7)-0)/1000 -> -23.215841 | M23: =(D12*0.3-(D12*0.3*0.501*$B$5/(0.501*$B$5+0.499*$B$6)*3%)-(D12*0.3*$B$8)-(D12*0.3*0.102477570147266)-(381600/4*$B$7)-0)/1000 -> -14.135379
A24: FCL B | B24: =(B12*0.1-(B12*0.1*0.501*$B$5/(0.501*$B$5+0.499*$B$6)*3%)-(B12*0.1*$B$8)-(B12*0.1*0.06)-(214800/4*$B$7)-8000)/1000 -> -64.038968 | C24: =(B12*0.2-(B12*0.2*0.501*$B$5/(0.501*$B$5+0.499*$B$6)*3%)-(B12*0.2*$B$8)-(B12*0.2*0.06)-(214800/4*$B$7)-0)/1000 -> -53.007937 | D24: =(B12*0.3-(B12*0.3*0.501*$B$5/(0.501*$B$5+0.499*$B$6)*3%)-(B12*0.3*$B$8)-(B12*0.3*0.06)-(214800/4*$B$7)-0)/1000 -> -49.976905 | E24: =(B12*0.4-(B12*0.4*0.501*$B$5/(0.501*$B$5+0.499*$B$6)*3%)-(B12*0.4*$B$8)-(B12*0.4*0.06)-(214800/4*$B$7)-0)/1000 -> -46.945874 | F24: =(C12*0.2-(C12*0.2*0.501*$B$5/(0.501*$B$5+0.499*$B$6)*3%)-(C12*0.2*$B$8)-(C12*0.2*0.0686323342495684)-(324000/4*$B$7)-24000)/1000 -> -89.083474 | G24: =(C12*0.23-(C12*0.23*0.501*$B$5/(0.501*$B$5+0.499*$B$6)*3%)-(C12*0.23*$B$8)-(C12*0.23*0.0686323342495684)-(324000/4*$B$7)-0)/1000 -> -61.480995 | H24: =(C12*0.27-(C12*0.27*0.501*$B$5/(0.501*$B$5+0.499*$B$6)*3%)-(C12*0.27*$B$8)-(C12*0.27*0.0686323342495684)-(324000/4*$B$7)-0)/1000 -> -56.67769 | I24: =(C12*0.3-(C12*0.3*0.501*$B$5/(0.501*$B$5+0.499*$B$6)*3%)-(C12*0.3*$B$8)-(C12*0.3*0.0686323342495684)-(324000/4*$B$7)-0)/1000 -> -53.075211 | J24: =(D12*0.2-(D12*0.2*0.501*$B$5/(0.501*$B$5+0.499*$B$6)*3%)-(D12*0.2*$B$8)-(D12*0.2*0.102477570147266)-(477600/4*$B$7)-48000)/1000 -> -118.80359 | K24: =(D12*0.23-(D12*0.23*0.501*$B$5/(0.501*$B$5+0.499*$B$6)*3%)-(D12*0.23*$B$8)-(D12*0.23*0.102477570147266)-(477600/4*$B$7)-0)/1000 -> -61.723124 | L24: =(D12*0.27-(D12*0.27*0.501*$B$5/(0.501*$B$5+0.499*$B$6)*3%)-(D12*0.27*$B$8)-(D12*0.27*0.102477570147266)-(477600/4*$B$7)-0)/1000 -> -49.615841 | M24: =(D12*0.3-(D12*0.3*0.501*$B$5/(0.501*$B$5+0.499*$B$6)*3%)-(D12*0.3*$B$8)-(D12*0.3*0.102477570147266)-(477600/4*$B$7)-0)/1000 -> -40.535379
A25: Cum A | B25: =B23 -> -23.118968 | C25: =B25+C23 -> -35.206905 | D25: =C25+D23 -> -44.263811 | E25: =D25+E23 -> -50.289685 | F25: =E25+F23 -> -104.94316 | G25: =F25+G23 -> -131.99415 | H25: =G25+H23 -> -154.24184 | I25: =H25+I23 -> -172.88705 | J25: =I25+J23 -> -265.29064 | ... M25: =L25+M23 -> -337.96498
A26: Cum B | B26: =B24 -> -64.038968 | C26: =B26+C24 -> -117.04691 | D26: =C26+D24 -> -167.02381 | E26: =D26+E24 -> -213.96968 | F26: =E26+F24 -> -303.05316 | G26: =F26+G24 -> -364.53415 | H26: =G26+H24 -> -421.21184 | I26: =H26+I24 -> -474.28705 | J26: =I26+J24 -> -593.09064 | ... M26: =L26+M24 -> -744.96498
A27: Tendencial | B27: T1 | C27: T2 | D27: T3 | E27: T4 | F27: T5 | G27: T6 | H27: T7 | I27: T8 | J27: T9 | K27: T10 | L27: T11 | M27: T12
A28: FCL A | B28: =(B13*0.1-(B13*0.1*0.501*$C$5/(0.501*$C$5+0.499*$C$6)*3%)-(B13*0.1*$C$8)-(B13*0.1*0.06)-(66000/4*$C$7)-8000)/1000 -> -18.003713 | C28: =(B13*0.2-(B13*0.2*0.501*$C$5/(0.501*$C$5+0.499*$C$6)*3%)-(B13*0.2*$C$8)-(B13*0.2*0.06)-(66000/4*$C$7)-0)/1000 -> -3.507426 | D28: =(B13*0.3-(B13*0.3*0.501*$C$5/(0.501*$C$5+0.499*$C$6)*3%)-(B13*0.3*$C$8)-(B13*0.3*0.06)-(66000/4*$C$7)-0)/1000 -> 2.988861 | E28: =(B13*0.4-(B13*0.4*0.501*$C$5/(0.501*$C$5+0.499*$C$6)*3%)-(B13*0.4*$C$8)-(B13*0.4*0.06)-(66000/4*$C$7)-0)/1000 -> 9.485148 | F28: =(C13*0.2-(C13*0.2*0.501*$C$5/(0.501*$C$5+0.499*$C$6)*3%)-(C13*0.2*$C$8)-(C13*0.2*0.0686323342495684)-(198800/4*$C$7)-24000)/1000 -> -22.220021 | G28: =(C13*0.23-(C13*0.23*0.501*$C$5/(0.501*$C$5+0.499*$C$6)*3%)-(C13*0.23*$C$8)-(C13*0.23*0.0686323342495684)-(198800/4*$C$7)-0)/1000 -> 9.5019763 | H28: =(C13*0.27-(C13*0.27*0.501*$C$5/(0.501*$C$5+0.499*$C$6)*3%)-(C13*0.27*$C$8)-(C13*0.27*0.0686323342495684)-(198800/4*$C$7)-0)/1000 -> 19.797972 | I28: =(C13*0.3-(C13*0.3*0.501*$C$5/(0.501*$C$5+0.499*$C$6)*3%)-(C13*0.3*$C$8)-(C13*0.3*0.0686323342495684)-(198800/4*$C$7)-0)/1000 -> 27.519969 | J28: =(D13*0.2-(D13*0.2*0.501*$C$5/(0.501*$C$5+0.499*$C$6)*3%)-(D13*0.2*$C$8)-(D13*0.2*0.102477570147266)-(381600/4*$C$7)-48000)/1000 -> -13.573126 | K28: =(D13*0.23-(D13*0.23*0.501*$C$5/(0.501*$C$5+0.499*$C$6)*3%)-(D13*0.23*$C$8)-(D13*0.23*0.102477570147266)-(381600/4*$C$7)-0)/1000 -> 53.900905 | L28: =(D13*0.27-(D13*0.27*0.501*$C$5/(0.501*$C$5+0.499*$C$6)*3%)-(D13*0.27*$C$8)-(D13*0.27*0.102477570147266)-(381600/4*$C$7)-0)/1000 -> 79.866279 | M28: =(D13*0.3-(D13*0.3*0.501*$C$5/(0.501*$C$5+0.499*$C$6)*3%)-(D13*0.3*$C$8)-(D13*0.3*0.102477570147266)-(381600/4*$C$7)-0)/1000 -> 99.34031
A29: FCL B | B29: =(B13*0.1-(B13*0.1*0.501*$C$5/(0.501*$C$5+0.499*$C$6)*3%)-(B13*0.1*$C$8)-(B13*0.1*0.06)-(214800/4*$C$7)-8000)/1000 -> -55.203713 | C29: =(B13*0.2-(B13*0.2*0.501*$C$5/(0.501*$C$5+0.499*$C$6)*3%)-(B13*0.2*$C$8)-(B13*0.2*0.06)-(214800/4*$C$7)-0)/1000 -> -40.707426 | D29: =(B13*0.3-(B13*0.3*0.501*$C$5/(0.501*$C$5+0.499*$C$6)*3%)-(B13*0.3*$C$8)-(B13*0.3*0.06)-(214800/4*$C$7)-0)/1000 -> -34.211139 | E29: =(B13*0.4-(B13*0.4*0.501*$C$5/(0.501*$C$5+0.499*$C$6)*3%)-(B13*0.4*$C$8)-(B13*0.4*0.06)-(214800/4*$C$7)-0)/1000 -> -27.714852 | F29: =(C13*0.2-(C13*0.2*0.501*$C$5/(0.501*$C$5+0.499*$C$6)*3%)-(C13*0.2*$C$8)-(C13*0.2*0.0686323342495684)-(324000/4*$C$7)-24000)/1000 -> -53.520021 | G29: =(C13*0.23-(C13*0.23*0.501*$C$5/(0.501*$C$5+0.499*$C$6)*3%)-(C13*0.23*$C$8)-(C13*0.23*0.0686323342495684)-(324000/4*$C$7)-0)/1000 -> -21.798024 | H29: =(C13*0.27-(C13*0.27*0.501*$C$5/(0.501*$C$5+0.499*$C$6)*3%)-(C13*0.27*$C$8)-(C13*0.27*0.0686323342495684)-(324000/4*$C$7)-0)/1000 -> -11.502028 | I29: =(C13*0.3-(C13*0.3*0.501*$C$5/(0.501*$C$5+0.499*$C$6)*3%)-(C13*0.3*$C$8)-(C13*0.3*0.0686323342495684)-(324000/4*$C$7)-0)/1000 -> -3.7800309 | J29: =(D13*0.2-(D13*0.2*0.501*$C$5/(0.501*$C$5+0.499*$C$6)*3%)-(D13*0.2*$C$8)-(D13*0.2*0.102477570147266)-(477600/4*$C$7)-48000)/1000 -> -37.573126 | K29: =(D13*0.23-(D13*0.23*0.501*$C$5/(0.501*$C$5+0.499*$C$6)*3%)-(D13*0.23*$C$8)-(D13*0.23*0.102477570147266)-(477600/4*$C$7)-0)/1000 -> 29.900905 | L29: =(D13*0.27-(D13*0.27*0.501*$C$5/(0.501*$C$5+0.499*$C$6)*3%)-(D13*0.27*$C$8)-(D13*0.27*0.102477570147266)-(477600/4*$C$7)-0)/1000 -> 55.866279 | M29: =(D13*0.3-(D13*0.3*0.501*$C$5/(0.501*$C$5+0.499*$C$6)*3%)-(D13*0.3*$C$8)-(D13*0.3*0.102477570147266)-(477600/4*$C$7)-0)/1000 -> 75.34031
A30: Cum A | B30: =B28 -> -18.003713 | C30: =B30+C28 -> -21.511139 | D30: =C30+D28 -> -18.522278 | E30: =D30+E28 -> -9.03713 | F30: =E30+F28 -> -31.257151 | G30: =F30+G28 -> -21.755174 | H30: =G30+H28 -> -1.957202 | I30: =H30+I28 -> 25.562767 | J30: =I30+J28 -> 11.989641 | ... M30: =L30+M28 -> 245.09713
A31: Cum B | B31: =B29 -> -55.203713 | C31: =B31+C29 -> -95.911139 | D31: =C31+D29 -> -130.12228 | E31: =D31+E29 -> -157.83713 | F31: =E31+F29 -> -211.35715 | G31: =F31+G29 -> -233.15517 | H31: =G31+H29 -> -244.6572 | I31: =H31+I29 -> -248.43723 | J31: =I31+J29 -> -286.01036 | ... M31: =L31+M29 -> -124.90287
A32: Otimista | B32: T1 | C32: T2 | D32: T3 | E32: T4 | F32: T5 | G32: T6 | H32: T7 | I32: T8 | J32: T9 | K32: T10 | L32: T11 | M32: T12
A33: FCL A | B33: =(B14*0.1-(B14*0.1*0.501*$D$5/(0.501*$D$5+0.499*$D$6)*3%)-(B14*0.1*$D$8)-(B14*0.1*0.06)-(66000/4*$D$7)-8000)/1000 -> -14.076076 | C33: =(B14*0.2-(B14*0.2*0.501*$D$5/(0.501*$D$5+0.499*$D$6)*3%)-(B14*0.2*$D$8)-(B14*0.2*0.06)-(66000/4*$D$7)-0)/1000 -> 3.5228476 | D33: =(B14*0.3-(B14*0.3*0.501*$D$5/(0.501*$D$5+0.499*$D$6)*3%)-(B14*0.3*$D$8)-(B14*0.3*0.06)-(66000/4*$D$7)-0)/1000 -> 13.121771 | E33: =(B14*0.4-(B14*0.4*0.501*$D$5/(0.501*$D$5+0.499*$D$6)*3%)-(B14*0.4*$D$8)-(B14*0.4*0.06)-(66000/4*$D$7)-0)/1000 -> 22.720695 | F33: =(C14*0.2-(C14*0.2*0.501*$D$5/(0.501*$D$5+0.499*$D$6)*3%)-(C14*0.2*$D$8)-(C14*0.2*0.0686323342495684)-(198800/4*$D$7)-24000)/1000 -> 4.8555957 | G33: =(C14*0.23-(C14*0.23*0.501*$D$5/(0.501*$D$5+0.499*$D$6)*3%)-(C14*0.23*$D$8)-(C14*0.23*0.0686323342495684)-(198800/4*$D$7)-0)/1000 -> 40.266185 | H33: =(C14*0.27-(C14*0.27*0.501*$D$5/(0.501*$D$5+0.499*$D$6)*3%)-(C14*0.27*$D$8)-(C14*0.27*0.0686323342495684)-(198800/4*$D$7)-0)/1000 -> 55.480304 | I33: =(C14*0.3-(C14*0.3*0.501*$D$5/(0.501*$D$5+0.499*$D$6)*3%)-(C14*0.3*$D$8)-(C14*0.3*0.0686323342495684)-(198800/4*$D$7)-0)/1000 -> 66.890894 | J33: =(D14*0.2-(D14*0.2*0.501*$D$5/(0.501*$D$5+0.499*$D$6)*3%)-(D14*0.2*$D$8)-(D14*0.2*0.102477570147266)-(381600/4*$D$7)-48000)/1000 -> 53.250059 | K33: =(D14*0.23-(D14*0.23*0.501*$D$5/(0.501*$D$5+0.499*$D$6)*3%)-(D14*0.23*$D$8)-(D14*0.23*0.102477570147266)-(381600/4*$D$7)-0)/1000 -> 130.03207 | L33: =(D14*0.27-(D14*0.27*0.501*$D$5/(0.501*$D$5+0.499*$D$6)*3%)-(D14*0.27*$D$8)-(D14*0.27*0.102477570147266)-(381600/4*$D$7)-0)/1000 -> 168.40808 | M33: =(D14*0.3-(D14*0.3*0.501*$D$5/(0.501*$D$5+0.499*$D$6)*3%)-(D14*0.3*$D$8)-(D14*0.3*0.102477570147266)-(381600/4*$D$7)-0)/1000 -> 197.19009
A34: FCL B | B34: =(B14*0.1-(B14*0.1*0.501*$D$5/(0.501*$D$5+0.499*$D$6)*3%)-(B14*0.1*$D$8)-(B14*0.1*0.06)-(214800/4*$D$7)-8000)/1000 -> -49.416076 | C34: =(B14*0.2-(B14*0.2*0.501*$D$5/(0.501*$D$5+0.499*$D$6)*3%)-(B14*0.2*$D$8)-(B14*0.2*0.06)-(214800/4*$D$7)-0)/1000 -> -31.817152 | D34: =(B14*0.3-(B14*0.3*0.501*$D$5/(0.501*$D$5+0.499*$D$6)*3%)-(B14*0.3*$D$8)-(B14*0.3*0.06)-(214800/4*$D$7)-0)/1000 -> -22.218229 | E34: =(B14*0.4-(B14*0.4*0.501*$D$5/(0.501*$D$5+0.499*$D$6)*3%)-(B14*0.4*$D$8)-(B14*0.4*0.06)-(214800/4*$D$7)-0)/1000 -> -12.619305 | F34: =(C14*0.2-(C14*0.2*0.501*$D$5/(0.501*$D$5+0.499*$D$6)*3%)-(C14*0.2*$D$8)-(C14*0.2*0.0686323342495684)-(324000/4*$D$7)-24000)/1000 -> -24.879404 | G34: =(C14*0.23-(C14*0.23*0.501*$D$5/(0.501*$D$5+0.499*$D$6)*3%)-(C14*0.23*$D$8)-(C14*0.23*0.0686323342495684)-(324000/4*$D$7)-0)/1000 -> 10.531185 | H34: =(C14*0.27-(C14*0.27*0.501*$D$5/(0.501*$D$5+0.499*$D$6)*3%)-(C14*0.27*$D$8)-(C14*0.27*0.0686323342495684)-(324000/4*$D$7)-0)/1000 -> 25.745304 | I34: =(C14*0.3-(C14*0.3*0.501*$D$5/(0.501*$D$5+0.499*$D$6)*3%)-(C14*0.3*$D$8)-(C14*0.3*0.0686323342495684)-(324000/4*$D$7)-0)/1000 -> 37.155894 | J34: =(D14*0.2-(D14*0.2*0.501*$D$5/(0.501*$D$5+0.499*$D$6)*3%)-(D14*0.2*$D$8)-(D14*0.2*0.102477570147266)-(477600/4*$D$7)-48000)/1000 -> 30.450059 | K34: =(D14*0.23-(D14*0.23*0.501*$D$5/(0.501*$D$5+0.499*$D$6)*3%)-(D14*0.23*$D$8)-(D14*0.23*0.102477570147266)-(477600/4*$D$7)-0)/1000 -> 107.23207 | L34: =(D14*0.27-(D14*0.27*0.501*$D$5/(0.501*$D$5+0.499*$D$6)*3%)-(D14*0.27*$D$8)-(D14*0.27*0.102477570147266)-(477600/4*$D$7)-0)/1000 -> 145.60808 | M34: =(D14*0.3-(D14*0.3*0.501*$D$5/(0.501*$D$5+0.499*$D$6)*3%)-(D14*0.3*$D$8)-(D14*0.3*0.102477570147266)-(477600/4*$D$7)-0)/1000 -> 174.39009
A35: Cum A | B35: =B33 -> -14.076076 | C35: =B35+C33 -> -10.553229 | D35: =C35+D33 -> 2.5685429 | E35: =D35+E33 -> 25.289238 | F35: =E35+F33 -> 30.144834 | G35: =F35+G33 -> 70.411019 | H35: =G35+H33 -> 125.89132 | I35: =H35+I33 -> 192.78222 | J35: =I35+J33 -> 246.03228 | ... M35: =L35+M33 -> 741.66251
A36: Cum B | B36: =B34 -> -49.416076 | C36: =B36+C34 -> -81.233229 | D36: =C36+D34 -> -103.45146 | E36: =D36+E34 -> -116.07076 | F36: =E36+F34 -> -140.95017 | G36: =F36+G34 -> -130.41898 | H36: =G36+H34 -> -104.67368 | I36: =H36+I34 -> -67.517783 | J36: =I36+J34 -> -37.067725 | ... M36: =L36+M34 -> 390.16251

Sheet DFC_Final_A
A1: ANTÉVIA — DFC Final E6 | Cenário A — Bootstrap / Founder-led | R$ mil
A3: Linha | B3: T1 | C3: T2 | D3: T3 | E3: T4 | F3: T5 | G3: T6 | H3: T7 | I3: T8 | J3: T9 | K3: T10 | L3: T11 | M3: T12
A4: ATIVIDADES OPERACIONAIS
A5: Receita Bruta | B5: =DFC_A!B4 -> 7.1797753 | C5: =DFC_A!C4 -> 14.160112 | D5: =DFC_A!D4 -> 21.339888 | E5: =DFC_A!E4 -> 28.320225 | F5: =DFC_A!F4 -> 56.640449 | G5: =DFC_A!G4 -> 65.216292 | H5: =DFC_A!H4 -> 76.783708 | I5: =DFC_A!I4 -> 85.359551 | ... M5: =DFC_A!M4 -> 223.12017
A6: (-) Impostos sobre receita | B6: =DFC_A!B8 -> -0.43078652 | C6: =DFC_A!C8 -> -0.84960674 | D6: =DFC_A!D8 -> -1.2803933 | E6: =DFC_A!E8 -> -1.6992135 | F6: =DFC_A!F8 -> -3.398427 | G6: =DFC_A!G8 -> -3.9129775 | H6: =DFC_A!H8 -> -5.4331672 | I6: =DFC_A!I8 -> -6.7470112 | ... M6: =DFC_A!M8 -> -25.011052
A7: (-) Custos transacionais | B7: =DFC_A!B5 -> -0.108 | C7: =DFC_A!C5 -> -0.213 | D7: =DFC_A!D5 -> -0.321 | E7: =DFC_A!E5 -> -0.426 | F7: =DFC_A!F5 -> -0.852 | G7: =DFC_A!G5 -> -0.981 | H7: =DFC_A!H5 -> -1.155 | I7: =DFC_A!I5 -> -1.284 | ... M7: =DFC_A!M5 -> -3.354
A8: (-) Perdas operacionais | B8: =DFC_A!B6 -> -0.071797753 | C8: =DFC_A!C6 -> -0.14160112 | D8: =DFC_A!D6 -> -0.21339888 | E8: =DFC_A!E6 -> -0.28320225 | F8: =DFC_A!F6 -> -0.56640449 | G8: =DFC_A!G6 -> -0.65216292 | H8: =DFC_A!H6 -> -0.76783708 | I8: =DFC_A!I6 -> -0.85359551 | ... M8: =DFC_A!M6 -> -2.2312017
A9: (=) Receita após tributos/custos variáveis | B9: =SUM(B5:B8) -> 6.569191 | C9: =SUM(C5:C8) -> 12.955904 | D9: =SUM(D5:D8) -> 19.525096 | E9: =SUM(E5:E8) -> 25.911809 | F9: =SUM(F5:F8) -> 51.823618 | G9: =SUM(G5:G8) -> 59.670152 | H9: =SUM(H5:H8) -> 69.427704 | I9: =SUM(I5:I8) -> 76.474944 | ... M9: =SUM(M5:M8) -> 192.52392
A10: (-) Custos de prestação / pessoal operacional | B10: =DFC_A!B7*0.65 -> -10.725 | C10: =DFC_A!C7*0.65 -> -10.725 | D10: =DFC_A!D7*0.65 -> -10.725 | E10: =DFC_A!E7*0.65 -> -10.725 | F10: =DFC_A!F7*0.65 -> -32.305 | G10: =DFC_A!G7*0.65 -> -32.305 | H10: =DFC_A!H7*0.65 -> -32.305 | I10: =DFC_A!I7*0.65 -> -32.305 | ... M10: =DFC_A!M7*0.65 -> -62.01
A11: (-) Despesas SG&A | B11: =DFC_A!B7*(1-0.65) -> -5.775 | C11: =DFC_A!C7*(1-0.65) -> -5.775 | D11: =DFC_A!D7*(1-0.65) -> -5.775 | E11: =DFC_A!E7*(1-0.65) -> -5.775 | F11: =DFC_A!F7*(1-0.65) -> -17.395 | G11: =DFC_A!G7*(1-0.65) -> -17.395 | H11: =DFC_A!H7*(1-0.65) -> -17.395 | I11: =DFC_A!I7*(1-0.65) -> -17.395 | ... M11: =DFC_A!M7*(1-0.65) -> -33.39
A12: (=) Resultado operacional de caixa | B12: =SUM(B9:B11) -> -9.930809 | C12: =SUM(C9:C11) -> -3.5440955 | D12: =SUM(D9:D11) -> 3.0250955 | E12: =SUM(E9:E11) -> 9.411809 | F12: =SUM(F9:F11) -> 2.123618 | G12: =SUM(G9:G11) -> 9.9701517 | H12: =SUM(H9:H11) -> 19.727704 | I12: =SUM(I9:I11) -> 26.774944 | ... M12: =SUM(M9:M11) -> 97.123918
A14: ATIVIDADES DE INVESTIMENTO
A15: (-) CAPEX / investimentos | B15: =DFC_A!B10 -> -8 | C15: =DFC_A!C10 -> 0 | D15: =DFC_A!D10 -> 0 | E15: =DFC_A!E10 -> 0 | F15: =DFC_A!F10 -> -24 | G15: =DFC_A!G10 -> 0 | H15: =DFC_A!H10 -> 0 | I15: =DFC_A!I10 -> 0 | ... M15: =DFC_A!M10 -> 0
A16: (=) Fluxo de Caixa Livre pré-financiamento | B16: =B12+B15 -> -17.930809 | C16: =C12+C15 -> -3.5440955 | D16: =D12+D15 -> 3.0250955 | E16: =E12+E15 -> 9.411809 | F16: =F12+F15 -> -21.876382 | G16: =G12+G15 -> 9.9701517 | H16: =H12+H15 -> 19.727704 | I16: =I12+I15 -> 26.774944 | ... M16: =M12+M15 -> 97.123918
A18: ATIVIDADES DE FINANCIAMENTO
A19: (+) Aporte de capital | B19: =DFC_A!B12 -> 47.414382 | C19: =DFC_A!C12 -> 0 | D19: =DFC_A!D12 -> 0 | E19: =DFC_A!E12 -> 0 | F19: =DFC_A!F12 -> 0 | G19: =DFC_A!G12 -> 0 | H19: =DFC_A!H12 -> 0 | I19: =DFC_A!I12 -> 0 | ... M19: =DFC_A!M12 -> 0
A20: (=) Variação líquida do caixa | B20: =B16+B19 -> 29.483573 | C20: =C16+C19 -> -3.5440955 | D20: =D16+D19 -> 3.0250955 | E20: =E16+E19 -> 9.411809 | F20: =F16+F19 -> -21.876382 | G20: =G16+G19 -> 9.9701517 | H20: =H16+H19 -> 19.727704 | I20: =I16+I19 -> 26.774944 | ... M20: =M16+M19 -> 97.123918
A21: (=) FC Acumulado | B21: =B20 -> 29.483573 | C21: =B21+C20 -> 25.939478 | D21: =C21+D20 -> 28.964573 | E21: =D21+E20 -> 38.376382 | F21: =E21+F20 -> 16.5 | G21: =F21+G20 -> 26.470152 | H21: =G21+H20 -> 46.197855 | I21: =H21+I20 -> 72.972799 | J21: =I21+J20 -> 61.60729 | ... M21: =L21+M20 -> 292.50549
A23: Nota de apresentação E6: a separação entre 'custos de prestação/pessoal operacional' e 'SG&A' usa uma alocação gerencial de 65% / 35% do OPEX do cenário A — Bootstrap / Founder-led. A DFC original preserva o OPEX total; esta abertura serve para aderir à estrutura acadêmica de Custos x Despesas. A alocação deve ser refinada quando houver folha e centros de custo definitivos.

Sheet DFC_Final_B
A1: ANTÉVIA — DFC Final E6 | Cenário B — Angel / Professional-led | R$ mil
A3: Linha | B3: T1 | C3: T2 | D3: T3 | E3: T4 | F3: T5 | G3: T6 | H3: T7 | I3: T8 | J3: T9 | K3: T10 | L3: T11 | M3: T12
A4: ATIVIDADES OPERACIONAIS
A5: Receita Bruta | B5: =DFC_B!B4 -> 7.1797753 | C5: =DFC_B!C4 -> 14.160112 | D5: =DFC_B!D4 -> 21.339888 | E5: =DFC_B!E4 -> 28.320225 | F5: =DFC_B!F4 -> 56.640449 | G5: =DFC_B!G4 -> 65.216292 | H5: =DFC_B!H4 -> 76.783708 | I5: =DFC_B!I4 -> 85.359551 | ... M5: =DFC_B!M4 -> 223.12017
A6: (-) Impostos sobre receita | B6: =DFC_B!B8 -> -0.43078652 | C6: =DFC_B!C8 -> -0.84960674 | D6: =DFC_B!D8 -> -1.2803933 | E6: =DFC_B!E8 -> -1.6992135 | F6: =DFC_B!F8 -> -3.398427 | G6: =DFC_B!G8 -> -3.9129775 | H6: =DFC_B!H8 -> -5.4331672 | I6: =DFC_B!I8 -> -6.7470112 | ... M6: =DFC_B!M8 -> -25.011052
A7: (-) Custos transacionais | B7: =DFC_B!B5 -> -0.108 | C7: =DFC_B!C5 -> -0.213 | D7: =DFC_B!D5 -> -0.321 | E7: =DFC_B!E5 -> -0.426 | F7: =DFC_B!F5 -> -0.852 | G7: =DFC_B!G5 -> -0.981 | H7: =DFC_B!H5 -> -1.155 | I7: =DFC_B!I5 -> -1.284 | ... M7: =DFC_B!M5 -> -3.354
A8: (-) Perdas operacionais | B8: =DFC_B!B6 -> -0.071797753 | C8: =DFC_B!C6 -> -0.14160112 | D8: =DFC_B!D6 -> -0.21339888 | E8: =DFC_B!E6 -> -0.28320225 | F8: =DFC_B!F6 -> -0.56640449 | G8: =DFC_B!G6 -> -0.65216292 | H8: =DFC_B!H6 -> -0.76783708 | I8: =DFC_B!I6 -> -0.85359551 | ... M8: =DFC_B!M6 -> -2.2312017
A9: (=) Receita após tributos/custos variáveis | B9: =SUM(B5:B8) -> 6.569191 | C9: =SUM(C5:C8) -> 12.955904 | D9: =SUM(D5:D8) -> 19.525096 | E9: =SUM(E5:E8) -> 25.911809 | F9: =SUM(F5:F8) -> 51.823618 | G9: =SUM(G5:G8) -> 59.670152 | H9: =SUM(H5:H8) -> 69.427704 | I9: =SUM(I5:I8) -> 76.474944 | ... M9: =SUM(M5:M8) -> 192.52392
A10: (-) Custos de prestação / pessoal operacional | B10: =DFC_B!B7*0.65 -> -34.905 | C10: =DFC_B!C7*0.65 -> -34.905 | D10: =DFC_B!D7*0.65 -> -34.905 | E10: =DFC_B!E7*0.65 -> -34.905 | F10: =DFC_B!F7*0.65 -> -52.65 | G10: =DFC_B!G7*0.65 -> -52.65 | H10: =DFC_B!H7*0.65 -> -52.65 | I10: =DFC_B!I7*0.65 -> -52.65 | ... M10: =DFC_B!M7*0.65 -> -77.61
A11: (-) Despesas SG&A | B11: =DFC_B!B7*(1-0.65) -> -18.795 | C11: =DFC_B!C7*(1-0.65) -> -18.795 | D11: =DFC_B!D7*(1-0.65) -> -18.795 | E11: =DFC_B!E7*(1-0.65) -> -18.795 | F11: =DFC_B!F7*(1-0.65) -> -28.35 | G11: =DFC_B!G7*(1-0.65) -> -28.35 | H11: =DFC_B!H7*(1-0.65) -> -28.35 | I11: =DFC_B!I7*(1-0.65) -> -28.35 | ... M11: =DFC_B!M7*(1-0.65) -> -41.79
A12: (=) Resultado operacional de caixa | B12: =SUM(B9:B11) -> -47.130809 | C12: =SUM(C9:C11) -> -40.744096 | D12: =SUM(D9:D11) -> -34.174904 | E12: =SUM(E9:E11) -> -27.788191 | F12: =SUM(F9:F11) -> -29.176382 | G12: =SUM(G9:G11) -> -21.329848 | H12: =SUM(H9:H11) -> -11.572296 | I12: =SUM(I9:I11) -> -4.5250562 | ... M12: =SUM(M9:M11) -> 73.123918
A14: ATIVIDADES DE INVESTIMENTO
A15: (-) CAPEX / investimentos | B15: =DFC_B!B10 -> -8 | C15: =DFC_B!C10 -> 0 | D15: =DFC_B!D10 -> 0 | E15: =DFC_B!E10 -> 0 | F15: =DFC_B!F10 -> -24 | G15: =DFC_B!G10 -> 0 | H15: =DFC_B!H10 -> 0 | I15: =DFC_B!I10 -> 0 | ... M15: =DFC_B!M10 -> 0
A16: (=) Fluxo de Caixa Livre pré-financiamento | B16: =B12+B15 -> -55.130809 | C16: =C12+C15 -> -40.744096 | D16: =D12+D15 -> -34.174904 | E16: =E12+E15 -> -27.788191 | F16: =F12+F15 -> -53.176382 | G16: =G12+G15 -> -21.329848 | H16: =H12+H15 -> -11.572296 | I16: =I12+I15 -> -4.5250562 | ... M16: =M12+M15 -> 73.123918
A18: ATIVIDADES DE FINANCIAMENTO
A19: (+) Aporte de capital | B19: =DFC_B!B12 -> 337.50709 | C19: =DFC_B!C12 -> 0 | D19: =DFC_B!D12 -> 0 | E19: =DFC_B!E12 -> 0 | F19: =DFC_B!F12 -> 0 | G19: =DFC_B!G12 -> 0 | H19: =DFC_B!H12 -> 0 | I19: =DFC_B!I12 -> 0 | ... M19: =DFC_B!M12 -> 0
A20: (=) Variação líquida do caixa | B20: =B16+B19 -> 282.37628 | C20: =C16+C19 -> -40.744096 | D20: =D16+D19 -> -34.174904 | E20: =E16+E19 -> -27.788191 | F20: =F16+F19 -> -53.176382 | G20: =G16+G19 -> -21.329848 | H20: =H16+H19 -> -11.572296 | I20: =I16+I19 -> -4.5250562 | ... M20: =M16+M19 -> 73.123918
A21: (=) FC Acumulado | B21: =B20 -> 282.37628 | C21: =B21+C20 -> 241.63219 | D21: =C21+D20 -> 207.45728 | E21: =D21+E20 -> 179.66909 | F21: =E21+F20 -> 126.49271 | G21: =F21+G20 -> 105.16286 | H21: =G21+H20 -> 93.590566 | I21: =H21+I20 -> 89.065509 | J21: =I21+J20 -> 53.7 | ... M21: =L21+M20 -> 212.5982
A23: Nota de apresentação E6: a separação entre 'custos de prestação/pessoal operacional' e 'SG&A' usa uma alocação gerencial de 65% / 35% do OPEX do cenário B — Angel / Professional-led. A DFC original preserva o OPEX total; esta abertura serve para aderir à estrutura acadêmica de Custos x Despesas. A alocação deve ser refinada quando houver folha e centros de custo definitivos.

Sheet Entregaveis_E6
A1: ANTÉVIA — Mapa de Entregáveis | Sprint E6
A3: Entregável do enunciado | B3: Situação | C3: Onde está | D3: Conteúdo-chave | E3: Premissa/GAP | F3: Vai ao Squeeze? | G3: Responsável | H3: Observação
A4: 1. Macroprocesso de negócio | B4: PARCIAL | C4: Material anterior / Squeeze | D4: Fluxo ponta a ponta da prestação | E4: Converter em visual final | F4: SIM | G4: Equipe | H4: Exigência explícita E6
A5: 2. Estrutura de pessoal | B5: PRONTO | C5: Premissas + DFC A/B | D5: Founder-led vs staff profissional | E5: Refinar cargos/salários se necessário | F5: SIM | G5: Equipe | H5: Evolução A1–A3
A6: 3. Custos, despesas e investimentos | B6: PRONTO | C6: Premissas + DFC_Final_A/B | D6: OPEX, custos variáveis, SG&A, CAPEX | E6: Alocação custos/SG&A é gerencial | F6: SIM | G6: Equipe | H6: 3 anos
A7: 4. DFC 3 anos | B7: PRONTO | C7: DFC_Final_A / DFC_Final_B | D7: Operação, investimento, financiamento | E7: Trimestral | F7: SIM | G7: Equipe | H7: 12 trimestres
A8: 3 cenários | B8: PRONTO | C8: Stress_Test | D8: Pessimista, tendencial, otimista | E8: Drivers explicitados | F8: SIM | G8: Equipe | H8: Exigência explícita E6
A9: Análise de sensibilidade | B9: PRONTO | C9: Stress_Test + Sensibilidade | D9: Volume, fee, comissão, OPEX, perdas | E9: Premissas E6 | F9: SIM | G9: Equipe | H9: Exigência explícita E6
A10: Memória de cálculo | B10: PRONTO | C10: Receita_v2 / Tributacao_v3 / Premissas | D10: Drivers auditáveis | E10: Hipóteses marcadas | F10: NÃO — apoio | G10: Equipe | H10: Munição para banca
A11: Financiamento A x B | B11: EXTRA | C11: Resumo / DFC A/B | D11: Bootstrap x Angel | E11: C descartado | F11: SIM — síntese | G11: Equipe | H11: Além do mínimo exigido
A13: Fonte do checklist: BD Sprint E6 — Resumo dos Entregáveis: macroprocesso; estrutura de pessoal; projeções de custos, despesas e investimentos; DFC por meses e/ou trimestres no período de 3 anos; e, no corpo da atividade, pelo menos três cenários com análise de sensibilidade.
A18: Slide | B18: Título | C18: Mensagem central | D18: Visual sugerido | E18: Números-chave | F18: Fonte na planilha | G18: Status | H18: Notas
A19: 1 | B19: Macroprocesso | C19: Como a Antévia entrega valor ponta a ponta | D19: Fluxo horizontal | E19: — | F19: Material macroprocesso | G19: PENDENTE | H19: Construir visual
A20: 2 | B20: Estrutura operacional | C20: A entrada founder-led reduz caixa; profissionalização compra capacidade | D20: Organograma A1→A3 | E20: A vs B | F20: Premissas | G20: PRONTO
A21: 3 | B21: Economia unitária | C21: Receita = fee + comissão, separada do GMV | D21: Waterfall por viagem | E21: ~R$100 fee + ~R$100 comissão | F21: Receita_v2 | G21: PRONTO
A22: 4 | B22: Custos, despesas e CAPEX | C22: Estrutura enxuta e escalável | D22: Barras por ano | E22: OPEX/CAPEX A/B | F22: Premissas | G22: PRONTO
A23: 5 | B23: DFC tendencial | C23: O bootstrap requer menos capital no cenário-base | D23: Curvas de caixa | E23: ~R$47–48k A; ~R$338–340k B | F23: DFC_Final_A/B | G23: PRONTO
A24: 6 | B24: Stress test | C24: A viabilidade é sensível à validação comercial | D24: 3 cenários | E24: Funding A/B por cenário | F24: Stress_Test | G24: PRONTO
A25: 7 | B25: Estrutura de capital | C25: Dívida foi testada e descartada; equity é capital paciente | D25: A vs B + nota C | E25: A founder-led; B angel | F25: Resumo | G25: PRONTO
A26: 8 | B26: Recomendação | C26: Começar A; migrar para B após marcos de validação | D26: Stage gates | E26: adesão, frequência, fee, comissão | F26: Stress_Test | G26: PRONTO

Sheet Cenarios_Oficiais_v6
A1: ANTÉVIA — Cenários Oficiais Recuperados do Sprint 04
A3: Cenário | B3: Ano 1 (R$) | C3: Ano 2 (R$) | D3: Ano 3 (R$) | E3: 3 anos (R$) | F3: Viagens 3 anos | G3: Alunos A1 | H3: Alunos T12
A4: Pessimista | B4: 38000 | C4: 140000 | D4: 372000 | E4: 550000 | F4: 2763 | G4: 50 | H4: 320
A5: Tendencial | B5: 71000 | C5: 284000 | D5: 744000 | E5: 1099000 | F5: 5508 | G5: 100 | H5: 650
A6: Otimista | B6: 113000 | C6: 455000 | D6: 1270000 | E6: 1838000 | F6: 9180 | G6: 160 | H6: 1100
A8: Fonte: trajetória da disciplina / Sprint 04 no deck compartilhado. A v6 restaura estes cenários como referência oficial. As variáveis 'escolas × elegíveis × adesão' introduzidas na v2 permanecem apenas como memória exploratória e NÃO são usadas na consolidação final.
A12: Driver oficial | B12: Pessimista | C12: Tendencial | D12: Otimista
A13: Alunos captados (referências A1/T12) | B13: 50 → 320 | C13: 100 → 650 | D13: 160 → 1.100
A14: Taxa de serviço | B14: Variável-chave | C14: Variável-chave | D14: Variável-chave
A15: Comissão | B15: Variável-chave | C15: Variável-chave | D15: Variável-chave
A17: Nota de fonte externa já validada no repositório: H6 (disposição a pagar R$50–150) segue 'a verificar'; portanto taxa de serviço e comissão devem permanecer hipóteses críticas, não fatos validados.

Sheet Viabilidade_S06
A1: ANTÉVIA — Sprint 06 | Indicadores de Viabilidade Econômico-Financeira
A3: Premissa | B3: Valor | C3: Unidade | D3: Status
A4: TMA anual | B4: 0.15 | C4: % a.a. | D4: Premissa E6/S06 — definir/validar
A5: TMA trimestral | B5: =(1+B4)^(1/4)-1 -> 0.035558076 | C5: % a.t. | D5: Calculada
A6: Horizonte | B6: 12 | C6: trimestres | D6: Sprint 06
A9: Indicador | B9: T1 | C9: T2 | D9: T3 | E9: T4 | F9: T5 | G9: T6 | H9: T7 | I9: T8 | J9: T9 | K9: T10 | L9: T11 | M9: T12 | N9: T0 | O9: T1 | P9: T2 | Q9: T3 | R9: T4 | S9: T5 | T9: T6 | U9: T7 | V9: T8 | W9: T9 | X9: T10 | Y9: T11 | Z9: T12
A10: FCL A — Tendencial (R$ mil) | B10: =DFC_Final_A!B16 -> -17.930809 | C10: =DFC_Final_A!C16 -> -3.5440955 | D10: =DFC_Final_A!D16 -> 3.0250955 | E10: =DFC_Final_A!E16 -> 9.411809 | F10: =DFC_Final_A!F16 -> -21.876382 | G10: =DFC_Final_A!G16 -> 9.9701517 | H10: =DFC_Final_A!H16 -> 19.727704 | I10: =DFC_Final_A!I16 -> 26.774944 | ... M10: =DFC_Final_A!M16 -> 97.123918 | N10: =-B15 -> -47.414382 | O10: =B10 -> -17.930809 | P10: =C10 -> -3.5440955 | Q10: =D10 -> 3.0250955 | R10: =E10 -> 9.411809 | S10: =F10 -> -21.876382 | T10: =G10 -> 9.9701517 | U10: =H10 -> 19.727704 | V10: =I10 -> 26.774944 | ... Z10: =M10 -> 97.123918
A11: FCL B — Tendencial (R$ mil) | B11: =DFC_Final_B!B16 -> -55.130809 | C11: =DFC_Final_B!C16 -> -40.744096 | D11: =DFC_Final_B!D16 -> -34.174904 | E11: =DFC_Final_B!E16 -> -27.788191 | F11: =DFC_Final_B!F16 -> -53.176382 | G11: =DFC_Final_B!G16 -> -21.329848 | H11: =DFC_Final_B!H16 -> -11.572296 | I11: =DFC_Final_B!I16 -> -4.5250562 | ... M11: =DFC_Final_B!M16 -> 73.123918 | N11: =-C15 -> -337.50709 | O11: =B11 -> -55.130809 | P11: =C11 -> -40.744096 | Q11: =D11 -> -34.174904 | R11: =E11 -> -27.788191 | S11: =F11 -> -53.176382 | T11: =G11 -> -21.329848 | U11: =H11 -> -11.572296 | V11: =I11 -> -4.5250562 | ... Z11: =M11 -> 73.123918
A14: Métrica | B14: A — Bootstrap | C14: B — Angel | D14: Unidade | E14: Interpretação | F14: Status
A15: Investimento/funding inicial | B15: =DFC_Final_A!B19 -> 47.414382 | C15: =DFC_Final_B!B19 -> 337.50709 | D15: R$ mil | E15: Capital inicial modelado | F15: Calculado
A16: VPL do projeto | B16: =-B15+NPV($B$5,B10:M10) -> 116.24984 | C16: =-C15+NPV($B$5,B11:M11) -> -476.70872 | D16: R$ mil | E16: VPL dos FCLs a TMA de 15% a.a. | F16: Calculado
A17: TIR trimestral | B17: =IRR(N10:Z10) -> 0.14401656 | C17: =IRR(N11:Z11) -> -0.1445208 | D17: % a.t. | E17: Retorno implícito | F17: Calculado
A18: TIR anual equivalente | B18: =(1+B17)^4-1 -> 0.71288908 | C18: =(1+C17)^4-1 -> -0.4644034 | D18: % a.a. | E18: Comparável à TMA | F18: Calculado
A19: Payback simples | B19: =IFERROR(MATCH(TRUE,B22:M22>=0,0),">12T") -> >12T | C19: =IFERROR(MATCH(TRUE,B23:M23>=0,0),">12T") -> >12T | D19: trimestres | E19: Primeiro trimestre com acumulado ≥ 0 | F19: Calculado
A20: Exposição máxima | B20: =-MIN(B22:M22) -> 78.328764 | C20: =-MIN(B23:M23) -> 621.31418 | D20: R$ mil | E20: Maior caixa acumulado negativo | F20: Calculado
A21: Acumulado / payback | B21: T1 | C21: T2 | D21: T3 | E21: T4 | F21: T5 | G21: T6 | H21: T7 | I21: T8 | J21: T9 | K21: T10 | L21: T11 | M21: T12
A22: A | B22: =-B15+B10 -> -65.345191 | C22: =B22+C10 -> -68.889287 | D22: =C22+D10 -> -65.864191 | E22: =D22+E10 -> -56.452382 | F22: =E22+F10 -> -78.328764 | G22: =F22+G10 -> -68.358612 | H22: =G22+H10 -> -48.630909 | I22: =H22+I10 -> -21.855965 | J22: =I22+J10 -> -33.221474 | ... M22: =L22+M10 -> 197.67672
A23: B | B23: =-C15+B11 -> -392.6379 | C23: =B23+C11 -> -433.382 | D23: =C23+D11 -> -467.5569 | E23: =D23+E11 -> -495.34509 | F23: =E23+F11 -> -548.52147 | G23: =F23+G11 -> -569.85132 | H23: =G23+H11 -> -581.42362 | I23: =H23+I11 -> -585.94868 | J23: =I23+J11 -> -621.31418 | ... M23: =L23+M11 -> -462.41599
A25: Primeiro resultado operacional positivo | B25: 3 | C25: 9 | D25: trimestre | E25: Primeiro trimestre em que o resultado operacional de caixa é > 0 | F25: Calculado — DFC final
A26: Metodologia: TMA de 15% a.a. é uma premissa de modelagem ainda não definida nas fontes recuperadas; fica em amarelo para decisão da equipe. VPL/TIR/Payback são calculados sobre o cenário tendencial e os FCLs trimestrais já modelados. Não interpretar o cenário B como valuation de equity do investidor: aqui mede-se a viabilidade econômica do projeto sob a estrutura B.

Sheet Plano_S06
A1: ANTÉVIA — Sprint 06 | Plano de Implementação
A3: Frente | B3: Entregável | C3: Conteúdo inicial | D3: Fonte | E3: Status | F3: Prioridade | G3: Dependência | H3: Próxima ação
A4: Viabilidade | B4: VPL / TIR / Payback | C4: Indicadores A e B com TMA parametrizada | D4: Viabilidade_S06 | E4: EM CURSO | F4: Alta | G4: Definir TMA | H4: Validar premissa
A5: Implementação | B5: EAP | C5: Pacotes: validação comercial, parceiros, MVP, operação, piloto, escala | D5: Sprint 06 | E5: PENDENTE | F5: Alta | G5: Macroprocesso | H5: Construir
A6: Implementação | B6: Cronograma | C6: Sequência e marcos de implantação | D6: Sprint 06 | E6: PENDENTE | F6: Alta | G6: EAP | H6: Construir
A7: Governança | B7: Matriz de responsabilidades | C7: RACI/RACIP por pacote de trabalho | D7: Sprint 06 | E7: PENDENTE | F7: Membros/roles | G7: Construir
A8: Gestão | B8: Marcos, indicadores e metas | C8: KPIs de validação, operação, financeiro e cliente | D8: Sprint 06 | E8: PENDENTE | F8: Hipóteses críticas | G8: Construir
A9: Risco | B9: Matriz de riscos | C9: Retomar H1–H8 e riscos operacionais/financeiros | D9: Sprint 01 + Sprint 06 | E9: PENDENTE | F9: Hipóteses | G9: Construir
A11: Riscos/hipóteses recuperados do Sprint 01: H1, H3, H4, H5 e H8 confirmadas; H2 e H6 a verificar; H7 parcialmente refutada. H6 (disposição a pagar R$50–150) permanece uma hipótese crítica para o plano de implementação.

Sheet E6_Cobertura
A1: ANTÉVIA — Sprint E6 | Auditoria de Cobertura dos Entregáveis
A3: Exigência | B3: Item a cobrir | C3: Situação | D3: Tratamento no modelo | E3: Natureza | F3: Vai ao Squeeze? | G3: Gap/ressalva
A4: Macroprocesso | B4: Etapas da prestação do serviço | C4: PRONTO CONCEITUAL | D4: 7 macroetapas + camada transversal | E4: Operacional | F4: SIM | G4: Falta somente diagrama final
A5: Pessoal | B5: Estrutura, times, salários, encargos, benefícios | C5: MODELADO COM RESSALVA | D5: A/B abertos por função, headcount, salário, encargos/benefícios e custo anual | E5: OPEX | F5: SIM | G5: Salários/carga de 40% são premissas a validar; OPEX total preservado
A6: Aquisição | B6: Custo de adquirir cliente/canais | C6: PARCIAL | D6: Marketing/prospecção dentro do OPEX | E6: SG&A | F6: SIM | G6: CAC isolado não está validado
A7: Prestação | B7: Custo para produzir/entregar serviço | C7: MODELADO | D7: Pessoal operacional + custos transacionais | E7: Custo | F7: SIM | G7: Alocação gerencial
A8: Pós-venda | B8: Custo de atender cliente | C8: MODELADO | D8: Ops/CS dentro do OPEX | E8: Custo | F8: SIM | G8: Sem centro de custo real
A9: Infraestrutura | B9: Estrutura física/ocupação | C9: MODELADO | D9: Estrutura enxuta / despesas administrativas | E9: SG&A/CAPEX | F9: NÃO | G9: Premissa de operação leve
A10: Tecnologia | B10: Sistemas/licenças/desenvolvimento | C10: MODELADO | D10: SaaS + CAPEX de tecnologia | E10: OPEX/CAPEX | F10: SIM | G10: Orçamentos reais não anexados
A11: Parceiros/sistemas | B11: Fornecedores e gestão | C11: MODELADO | D11: Comissões/serviços/SaaS | E11: Custo/SG&A | F11: NÃO | G11: Comissão é hipótese crítica
A12: Administrativo | B12: Contábil, geral, gestão | C12: MODELADO | D12: OPEX administrativo | E12: SG&A | F12: NÃO | G12: Estimativa
A13: Marketing/prospecção | B13: Aquisição e comercial | C13: MODELADO | D13: OPEX comercial | E13: SG&A | F13: SIM | G13: CAC a validar
A14: Bancário/cobrança | B14: Meios de pagamento | C14: MODELADO | D14: 3% sobre fee | E14: Custo variável | F14: SIM | G14: Premissa
... A18: Cenários | B18: Pessimista/tendencial/otimista | C18: CORRIGIDO | D18: Cenários originais do Sprint anterior | E18: Sensibilidade | F18: SIM | G18: Receitas restauradas
A20: Base da auditoria: BD Sprint E6 — Projeções Eco-Fin Parte 2, especialmente as questões das páginas 2–3 e o resumo dos quatro entregáveis da página 5. A planilha distingue itens modelados de itens ainda não validados; não transforma estimativas em dados observados.

Sheet E6_Cenarios_Final
A1: ANTÉVIA — E6 | Cenários Pessimista, Tendencial e Otimista
A3: Cenário | B3: Receita A1 | C3: Receita A2 | D3: Receita A3 | E3: Receita 3a | F3: Viagens 3a | G3: OPEX fator | H3: Perdas | I3: Funding A | J3: Funding B
A4: Pessimista | B4: 38000 | C4: 140000 | D4: 372000 | E4: 550000 | F4: 2763 | G4: 1.1 | H4: 0.02 | I4: =-MIN(0,MIN(B12:M12))+16500/1000*$G$4 -> 328.46668 | J4: =-MIN(0,MIN(B14:M14))+53700/1000*$G$4 -> 776.38668
A5: Tendencial | B5: 71000 | C5: 284000 | D5: 744000 | E5: 1099000 | F5: 5508 | G5: 1 | H5: 0.01 | I5: =E6_DFC_A_Final!B15 -> 47.414382 | J5: =E6_DFC_B_Final!B15 -> 337.50709
A6: Otimista | B6: 113000 | C6: 455000 | D6: 1270000 | E6: 1838000 | F6: 9180 | G6: 0.95 | H6: 0.005 | I6: =-MIN(0,MIN(B24:M24))+16500/1000*$G$6 -> 28.954339 | J6: =-MIN(0,MIN(B26:M26))+53700/1000*$G$6 -> 177.13666
A10: Pessimista | B10: T1 | C10: T2 | D10: T3 | E10: T4 | F10: T5 | G10: T6 | H10: T7 | I10: T8 | J10: T9 | K10: T10 | L10: T11 | M10: T12
A11: FCL A | B11: =($B$4*0.1-($B$4*0.1*0.501*3%)-($B$4*0.1*0.06)-($B$4*0.1*$H$4)-66000/4*$G$4-8000)/1000 -> -22.711114 | C11: =($B$4*0.2-($B$4*0.2*0.501*3%)-($B$4*0.2*0.06)-($B$4*0.2*$H$4)-66000/4*$G$4-0)/1000 -> -11.272228 | D11: =($B$4*0.3-($B$4*0.3*0.501*3%)-($B$4*0.3*0.06)-($B$4*0.3*$H$4)-66000/4*$G$4-0)/1000 -> -7.833342 | E11: =($B$4*0.4-($B$4*0.4*0.501*3%)-($B$4*0.4*0.06)-($B$4*0.4*$H$4)-66000/4*$G$4-0)/1000 -> -4.394456 | F11: =($C$4*0.2-($C$4*0.2*0.501*3%)-($C$4*0.2*0.0686323342495684)-($C$4*0.2*$H$4)-198800/4*$G$4-24000)/1000 -> -53.572545 | G11: =($C$4*0.23-($C$4*0.23*0.501*3%)-($C$4*0.23*0.0686323342495684)-($C$4*0.23*$H$4)-198800/4*$G$4-0)/1000 -> -25.807927 | H11: =($C$4*0.27-($C$4*0.27*0.501*3%)-($C$4*0.27*0.0686323342495684)-($C$4*0.27*$H$4)-198800/4*$G$4-0)/1000 -> -20.788436 | I11: =($C$4*0.3-($C$4*0.3*0.501*3%)-($C$4*0.3*0.0686323342495684)-($C$4*0.3*$H$4)-198800/4*$G$4-0)/1000 -> -17.023818 | J11: =($D$4*0.2-($D$4*0.2*0.501*3%)-($D$4*0.2*0.102477570147266)-($D$4*0.2*$H$4)-381600/4*$G$4-48000)/1000 -> -88.770563 | K11: =($D$4*0.23-($D$4*0.23*0.501*3%)-($D$4*0.23*0.102477570147266)-($D$4*0.23*$H$4)-381600/4*$G$4-0)/1000 -> -31.145148 | L11: =($D$4*0.27-($D$4*0.27*0.501*3%)-($D$4*0.27*0.102477570147266)-($D$4*0.27*$H$4)-381600/4*$G$4-0)/1000 -> -18.31126 | M11: =($D$4*0.3-($D$4*0.3*0.501*3%)-($D$4*0.3*0.102477570147266)-($D$4*0.3*$H$4)-381600/4*$G$4-0)/1000 -> -8.6858448
A12: Acum A | B12: =B11 -> -22.711114 | C12: =B12+C11 -> -33.983342 | D12: =C12+D11 -> -41.816684 | E12: =D12+E11 -> -46.21114 | F12: =E12+F11 -> -99.783685 | G12: =F12+G11 -> -125.59161 | H12: =G12+H11 -> -146.38005 | I12: =H12+I11 -> -163.40387 | J12: =I12+J11 -> -252.17443 | ... M12: =L12+M11 -> -310.31668
A13: FCL B | B13: =($B$4*0.1-($B$4*0.1*0.501*3%)-($B$4*0.1*0.06)-($B$4*0.1*$H$4)-214800/4*$G$4-8000)/1000 -> -63.631114 | C13: =($B$4*0.2-($B$4*0.2*0.501*3%)-($B$4*0.2*0.06)-($B$4*0.2*$H$4)-214800/4*$G$4-0)/1000 -> -52.192228 | D13: =($B$4*0.3-($B$4*0.3*0.501*3%)-($B$4*0.3*0.06)-($B$4*0.3*$H$4)-214800/4*$G$4-0)/1000 -> -48.753342 | E13: =($B$4*0.4-($B$4*0.4*0.501*3%)-($B$4*0.4*0.06)-($B$4*0.4*$H$4)-214800/4*$G$4-0)/1000 -> -45.314456 | F13: =($C$4*0.2-($C$4*0.2*0.501*3%)-($C$4*0.2*0.0686323342495684)-($C$4*0.2*$H$4)-324000/4*$G$4-24000)/1000 -> -88.002545 | G13: =($C$4*0.23-($C$4*0.23*0.501*3%)-($C$4*0.23*0.0686323342495684)-($C$4*0.23*$H$4)-324000/4*$G$4-0)/1000 -> -60.237927 | H13: =($C$4*0.27-($C$4*0.27*0.501*3%)-($C$4*0.27*0.0686323342495684)-($C$4*0.27*$H$4)-324000/4*$G$4-0)/1000 -> -55.218436 | I13: =($C$4*0.3-($C$4*0.3*0.501*3%)-($C$4*0.3*0.0686323342495684)-($C$4*0.3*$H$4)-324000/4*$G$4-0)/1000 -> -51.453818 | J13: =($D$4*0.2-($D$4*0.2*0.501*3%)-($D$4*0.2*0.102477570147266)-($D$4*0.2*$H$4)-477600/4*$G$4-48000)/1000 -> -115.17056 | K13: =($D$4*0.23-($D$4*0.23*0.501*3%)-($D$4*0.23*0.102477570147266)-($D$4*0.23*$H$4)-477600/4*$G$4-0)/1000 -> -57.545148 | L13: =($D$4*0.27-($D$4*0.27*0.501*3%)-($D$4*0.27*0.102477570147266)-($D$4*0.27*$H$4)-477600/4*$G$4-0)/1000 -> -44.71126 | M13: =($D$4*0.3-($D$4*0.3*0.501*3%)-($D$4*0.3*0.102477570147266)-($D$4*0.3*$H$4)-477600/4*$G$4-0)/1000 -> -35.085845
A14: Acum B | B14: =B13 -> -63.631114 | C14: =B14+C13 -> -115.82334 | D14: =C14+D13 -> -164.57668 | E14: =D14+E13 -> -209.89114 | F14: =E14+F13 -> -297.89369 | G14: =F14+G13 -> -358.13161 | H14: =G14+H13 -> -413.35005 | I14: =H14+I13 -> -464.80387 | J14: =I14+J13 -> -579.97443 | ... M14: =L14+M13 -> -717.31668
A16: Tendencial | B16: T1 | C16: T2 | D16: T3 | E16: T4 | F16: T5 | G16: T6 | H16: T7 | I16: T8 | J16: T9 | K16: T10 | L16: T11 | M16: T12
A17: FCL A | B17: =($B$5*0.1-($B$5*0.1*0.501*3%)-($B$5*0.1*0.06)-($B$5*0.1*$H$5)-66000/4*$G$5-8000)/1000 -> -18.003713 | C17: =($B$5*0.2-($B$5*0.2*0.501*3%)-($B$5*0.2*0.06)-($B$5*0.2*$H$5)-66000/4*$G$5-0)/1000 -> -3.507426 | D17: =($B$5*0.3-($B$5*0.3*0.501*3%)-($B$5*0.3*0.06)-($B$5*0.3*$H$5)-66000/4*$G$5-0)/1000 -> 2.988861 | E17: =($B$5*0.4-($B$5*0.4*0.501*3%)-($B$5*0.4*0.06)-($B$5*0.4*$H$5)-66000/4*$G$5-0)/1000 -> 9.485148 | F17: =($C$5*0.2-($C$5*0.2*0.501*3%)-($C$5*0.2*0.0686323342495684)-($C$5*0.2*$H$5)-198800/4*$G$5-24000)/1000 -> -22.220021 | G17: =($C$5*0.23-($C$5*0.23*0.501*3%)-($C$5*0.23*0.0686323342495684)-($C$5*0.23*$H$5)-198800/4*$G$5-0)/1000 -> 9.5019763 | H17: =($C$5*0.27-($C$5*0.27*0.501*3%)-($C$5*0.27*0.0686323342495684)-($C$5*0.27*$H$5)-198800/4*$G$5-0)/1000 -> 19.797972 | I17: =($C$5*0.3-($C$5*0.3*0.501*3%)-($C$5*0.3*0.0686323342495684)-($C$5*0.3*$H$5)-198800/4*$G$5-0)/1000 -> 27.519969 | J17: =($D$5*0.2-($D$5*0.2*0.501*3%)-($D$5*0.2*0.102477570147266)-($D$5*0.2*$H$5)-381600/4*$G$5-48000)/1000 -> -13.573126 | K17: =($D$5*0.23-($D$5*0.23*0.501*3%)-($D$5*0.23*0.102477570147266)-($D$5*0.23*$H$5)-381600/4*$G$5-0)/1000 -> 53.900905 | L17: =($D$5*0.27-($D$5*0.27*0.501*3%)-($D$5*0.27*0.102477570147266)-($D$5*0.27*$H$5)-381600/4*$G$5-0)/1000 -> 79.866279 | M17: =($D$5*0.3-($D$5*0.3*0.501*3%)-($D$5*0.3*0.102477570147266)-($D$5*0.3*$H$5)-381600/4*$G$5-0)/1000 -> 99.34031
A18: Acum A | B18: =B17 -> -18.003713 | C18: =B18+C17 -> -21.511139 | D18: =C18+D17 -> -18.522278 | E18: =D18+E17 -> -9.03713 | F18: =E18+F17 -> -31.257151 | G18: =F18+G17 -> -21.755174 | H18: =G18+H17 -> -1.957202 | I18: =H18+I17 -> 25.562767 | J18: =I18+J17 -> 11.989641 | ... M18: =L18+M17 -> 245.09713
A19: FCL B | B19: =($B$5*0.1-($B$5*0.1*0.501*3%)-($B$5*0.1*0.06)-($B$5*0.1*$H$5)-214800/4*$G$5-8000)/1000 -> -55.203713 | C19: =($B$5*0.2-($B$5*0.2*0.501*3%)-($B$5*0.2*0.06)-($B$5*0.2*$H$5)-214800/4*$G$5-0)/1000 -> -40.707426 | D19: =($B$5*0.3-($B$5*0.3*0.501*3%)-($B$5*0.3*0.06)-($B$5*0.3*$H$5)-214800/4*$G$5-0)/1000 -> -34.211139 | E19: =($B$5*0.4-($B$5*0.4*0.501*3%)-($B$5*0.4*0.06)-($B$5*0.4*$H$5)-214800/4*$G$5-0)/1000 -> -27.714852 | F19: =($C$5*0.2-($C$5*0.2*0.501*3%)-($C$5*0.2*0.0686323342495684)-($C$5*0.2*$H$5)-324000/4*$G$5-24000)/1000 -> -53.520021 | G19: =($C$5*0.23-($C$5*0.23*0.501*3%)-($C$5*0.23*0.0686323342495684)-($C$5*0.23*$H$5)-324000/4*$G$5-0)/1000 -> -21.798024 | H19: =($C$5*0.27-($C$5*0.27*0.501*3%)-($C$5*0.27*0.0686323342495684)-($C$5*0.27*$H$5)-324000/4*$G$5-0)/1000 -> -11.502028 | I19: =($C$5*0.3-($C$5*0.3*0.501*3%)-($C$5*0.3*0.0686323342495684)-($C$5*0.3*$H$5)-324000/4*$G$5-0)/1000 -> -3.7800309 | J19: =($D$5*0.2-($D$5*0.2*0.501*3%)-($D$5*0.2*0.102477570147266)-($D$5*0.2*$H$5)-477600/4*$G$5-48000)/1000 -> -37.573126 | K19: =($D$5*0.23-($D$5*0.23*0.501*3%)-($D$5*0.23*0.102477570147266)-($D$5*0.23*$H$5)-477600/4*$G$5-0)/1000 -> 29.900905 | L19: =($D$5*0.27-($D$5*0.27*0.501*3%)-($D$5*0.27*0.102477570147266)-($D$5*0.27*$H$5)-477600/4*$G$5-0)/1000 -> 55.866279 | M19: =($D$5*0.3-($D$5*0.3*0.501*3%)-($D$5*0.3*0.102477570147266)-($D$5*0.3*$H$5)-477600/4*$G$5-0)/1000 -> 75.34031
A20: Acum B | B20: =B19 -> -55.203713 | C20: =B20+C19 -> -95.911139 | D20: =C20+D19 -> -130.12228 | E20: =D20+E19 -> -157.83713 | F20: =E20+F19 -> -211.35715 | G20: =F20+G19 -> -233.15517 | H20: =G20+H19 -> -244.6572 | I20: =H20+I19 -> -248.43723 | J20: =I20+J19 -> -286.01036 | ... M20: =L20+M19 -> -124.90287
A22: Otimista | B22: T1 | C22: T2 | D22: T3 | E22: T4 | F22: T5 | G22: T6 | H22: T7 | I22: T8 | J22: T9 | K22: T10 | L22: T11 | M22: T12
A23: FCL A | B23: =($B$6*0.1-($B$6*0.1*0.501*3%)-($B$6*0.1*0.06)-($B$6*0.1*$H$6)-66000/4*$G$6-8000)/1000 -> -13.279339 | C23: =($B$6*0.2-($B$6*0.2*0.501*3%)-($B$6*0.2*0.06)-($B$6*0.2*$H$6)-66000/4*$G$6-0)/1000 -> 5.116322 | D23: =($B$6*0.3-($B$6*0.3*0.501*3%)-($B$6*0.3*0.06)-($B$6*0.3*$H$6)-66000/4*$G$6-0)/1000 -> 15.511983 | E23: =($B$6*0.4-($B$6*0.4*0.501*3%)-($B$6*0.4*0.06)-($B$6*0.4*$H$6)-66000/4*$G$6-0)/1000 -> 25.907644 | F23: =($C$6*0.2-($C$6*0.2*0.501*3%)-($C$6*0.2*0.0686323342495684)-($C$6*0.2*$H$6)-198800/4*$G$6-24000)/1000 -> 11.716728 | G23: =($C$6*0.23-($C$6*0.23*0.501*3%)-($C$6*0.23*0.0686323342495684)-($C$6*0.23*$H$6)-198800/4*$G$6-0)/1000 -> 48.156487 | H23: =($C$6*0.27-($C$6*0.27*0.501*3%)-($C$6*0.27*0.0686323342495684)-($C$6*0.27*$H$6)-198800/4*$G$6-0)/1000 -> 64.742832 | I23: =($C$6*0.3-($C$6*0.3*0.501*3%)-($C$6*0.3*0.0686323342495684)-($C$6*0.3*$H$6)-198800/4*$G$6-0)/1000 -> 77.182591 | J23: =($D$6*0.2-($D$6*0.2*0.501*3%)-($D$6*0.2*0.102477570147266)-($D$6*0.2*$H$6)-381600/4*$G$6-48000)/1000 -> 84.253077 | K23: =($D$6*0.23-($D$6*0.23*0.501*3%)-($D$6*0.23*0.102477570147266)-($D$6*0.23*$H$6)-381600/4*$G$6-0)/1000 -> 165.68554 | L23: =($D$6*0.27-($D$6*0.27*0.501*3%)-($D$6*0.27*0.102477570147266)-($D$6*0.27*$H$6)-381600/4*$G$6-0)/1000 -> 210.26215 | M23: =($D$6*0.3-($D$6*0.3*0.501*3%)-($D$6*0.3*0.102477570147266)-($D$6*0.3*$H$6)-381600/4*$G$6-0)/1000 -> 243.69462
A24: Acum A | B24: =B23 -> -13.279339 | C24: =B24+C23 -> -8.163017 | D24: =C24+D23 -> 7.348966 | E24: =D24+E23 -> 33.25661 | F24: =E24+F23 -> 44.973338 | G24: =F24+G23 -> 93.129824 | H24: =G24+H23 -> 157.87266 | I24: =H24+I23 -> 235.05525 | J24: =I24+J23 -> 319.30833 | ... M24: =L24+M23 -> 938.95063
A25: FCL B | B25: =($B$6*0.1-($B$6*0.1*0.501*3%)-($B$6*0.1*0.06)-($B$6*0.1*$H$6)-214800/4*$G$6-8000)/1000 -> -48.619339 | C25: =($B$6*0.2-($B$6*0.2*0.501*3%)-($B$6*0.2*0.06)-($B$6*0.2*$H$6)-214800/4*$G$6-0)/1000 -> -30.223678 | D25: =($B$6*0.3-($B$6*0.3*0.501*3%)-($B$6*0.3*0.06)-($B$6*0.3*$H$6)-214800/4*$G$6-0)/1000 -> -19.828017 | E25: =($B$6*0.4-($B$6*0.4*0.501*3%)-($B$6*0.4*0.06)-($B$6*0.4*$H$6)-214800/4*$G$6-0)/1000 -> -9.432356 | F25: =($C$6*0.2-($C$6*0.2*0.501*3%)-($C$6*0.2*0.0686323342495684)-($C$6*0.2*$H$6)-324000/4*$G$6-24000)/1000 -> -18.018272 | G25: =($C$6*0.23-($C$6*0.23*0.501*3%)-($C$6*0.23*0.0686323342495684)-($C$6*0.23*$H$6)-324000/4*$G$6-0)/1000 -> 18.421487 | H25: =($C$6*0.27-($C$6*0.27*0.501*3%)-($C$6*0.27*0.0686323342495684)-($C$6*0.27*$H$6)-324000/4*$G$6-0)/1000 -> 35.007832 | I25: =($C$6*0.3-($C$6*0.3*0.501*3%)-($C$6*0.3*0.0686323342495684)-($C$6*0.3*$H$6)-324000/4*$G$6-0)/1000 -> 47.447591 | J25: =($D$6*0.2-($D$6*0.2*0.501*3%)-($D$6*0.2*0.102477570147266)-($D$6*0.2*$H$6)-477600/4*$G$6-48000)/1000 -> 61.453077 | K25: =($D$6*0.23-($D$6*0.23*0.501*3%)-($D$6*0.23*0.102477570147266)-($D$6*0.23*$H$6)-477600/4*$G$6-0)/1000 -> 142.88554 | L25: =($D$6*0.27-($D$6*0.27*0.501*3%)-($D$6*0.27*0.102477570147266)-($D$6*0.27*$H$6)-477600/4*$G$6-0)/1000 -> 187.46215 | M25: =($D$6*0.3-($D$6*0.3*0.501*3%)-($D$6*0.3*0.102477570147266)-($D$6*0.3*$H$6)-477600/4*$G$6-0)/1000 -> 220.89462
A26: Acum B | B26: =B25 -> -48.619339 | C26: =B26+C25 -> -78.843017 | D26: =C26+D25 -> -98.671034 | E26: =D26+E25 -> -108.10339 | F26: =E26+F25 -> -126.12166 | G26: =F26+G25 -> -107.70018 | H26: =G26+H25 -> -72.692343 | I26: =H26+I25 -> -25.244752 | J26: =I26+J25 -> 36.208325 | ... M26: =L26+M25 -> 587.45063
A29: Cenários de receita restaurados da trajetória anterior do projeto. Para o E6 Parte 2, o stress de custos é gerencial: OPEX +10% no pessimista e -5% no otimista; perdas 2% / 1% / 0,5%. No cenário tendencial, Funding A/B está ancorado nos DFCs finais oficiais (E6_DFC_A_Final e E6_DFC_B_Final) para eliminar divergência entre consolidações. As linhas trimestrais desta aba permanecem como motor de sensibilidade e podem apresentar pequenas diferenças de granularidade.

Sheet E6_DFC_A_Final
A1: ANTÉVIA — E6 | DFC A — Bootstrap / Founder-led | R$ mil
A3: Linha | B3: T1 | C3: T2 | D3: T3 | E3: T4 | F3: T5 | G3: T6 | H3: T7 | I3: T8 | J3: T9 | K3: T10 | L3: T11 | M3: T12
A4: Receita Bruta | B4: =DFC_A!B4 -> 7.1797753 | C4: =DFC_A!C4 -> 14.160112 | D4: =DFC_A!D4 -> 21.339888 | E4: =DFC_A!E4 -> 28.320225 | F4: =DFC_A!F4 -> 56.640449 | G4: =DFC_A!G4 -> 65.216292 | H4: =DFC_A!H4 -> 76.783708 | I4: =DFC_A!I4 -> 85.359551 | ... M4: =DFC_A!M4 -> 223.12017
A5: (-) Impostos sobre receita | B5: =DFC_A!B8 -> -0.43078652 | C5: =DFC_A!C8 -> -0.84960674 | D5: =DFC_A!D8 -> -1.2803933 | E5: =DFC_A!E8 -> -1.6992135 | F5: =DFC_A!F8 -> -3.398427 | G5: =DFC_A!G8 -> -3.9129775 | H5: =DFC_A!H8 -> -5.4331672 | I5: =DFC_A!I8 -> -6.7470112 | ... M5: =DFC_A!M8 -> -25.011052
A6: (-) Custos transacionais | B6: =DFC_A!B5 -> -0.108 | C6: =DFC_A!C5 -> -0.213 | D6: =DFC_A!D5 -> -0.321 | E6: =DFC_A!E5 -> -0.426 | F6: =DFC_A!F5 -> -0.852 | G6: =DFC_A!G5 -> -0.981 | H6: =DFC_A!H5 -> -1.155 | I6: =DFC_A!I5 -> -1.284 | ... M6: =DFC_A!M5 -> -3.354
A7: (-) Perdas operacionais | B7: =DFC_A!B6 -> -0.071797753 | C7: =DFC_A!C6 -> -0.14160112 | D7: =DFC_A!D6 -> -0.21339888 | E7: =DFC_A!E6 -> -0.28320225 | F7: =DFC_A!F6 -> -0.56640449 | G7: =DFC_A!G6 -> -0.65216292 | H7: =DFC_A!H6 -> -0.76783708 | I7: =DFC_A!I6 -> -0.85359551 | ... M7: =DFC_A!M6 -> -2.2312017
A8: (=) Receita Líquida gerencial | B8: =SUM(B4:B7) -> 6.569191 | C8: =SUM(C4:C7) -> 12.955904 | D8: =SUM(D4:D7) -> 19.525096 | E8: =SUM(E4:E7) -> 25.911809 | F8: =SUM(F4:F7) -> 51.823618 | G8: =SUM(G4:G7) -> 59.670152 | H8: =SUM(H4:H7) -> 69.427704 | I8: =SUM(I4:I7) -> 76.474944 | ... M8: =SUM(M4:M7) -> 192.52392
A9: (-) Total de custos | B9: =DFC_A!B7*0.6 -> -9.9 | C9: =DFC_A!C7*0.6 -> -9.9 | D9: =DFC_A!D7*0.6 -> -9.9 | E9: =DFC_A!E7*0.6 -> -9.9 | F9: =DFC_A!F7*0.6 -> -29.82 | G9: =DFC_A!G7*0.6 -> -29.82 | H9: =DFC_A!H7*0.6 -> -29.82 | I9: =DFC_A!I7*0.6 -> -29.82 | ... M9: =DFC_A!M7*0.6 -> -57.24
A10: (=) Contribuição Bruta | B10: =B8+B9 -> -3.330809 | C10: =C8+C9 -> 3.0559045 | D10: =D8+D9 -> 9.6250955 | E10: =E8+E9 -> 16.011809 | F10: =F8+F9 -> 22.003618 | G10: =G8+G9 -> 29.850152 | H10: =H8+H9 -> 39.607704 | I10: =I8+I9 -> 46.654944 | ... M10: =M8+M9 -> 135.28392
A11: (-) Total de despesas (SG&A) | B11: =DFC_A!B7*(1-0.6) -> -6.6 | C11: =DFC_A!C7*(1-0.6) -> -6.6 | D11: =DFC_A!D7*(1-0.6) -> -6.6 | E11: =DFC_A!E7*(1-0.6) -> -6.6 | F11: =DFC_A!F7*(1-0.6) -> -19.88 | G11: =DFC_A!G7*(1-0.6) -> -19.88 | H11: =DFC_A!H7*(1-0.6) -> -19.88 | I11: =DFC_A!I7*(1-0.6) -> -19.88 | ... M11: =DFC_A!M7*(1-0.6) -> -38.16
A12: (=) Resultado operacional de caixa | B12: =B10+B11 -> -9.930809 | C12: =C10+C11 -> -3.5440955 | D12: =D10+D11 -> 3.0250955 | E12: =E10+E11 -> 9.411809 | F12: =F10+F11 -> 2.123618 | G12: =G10+G11 -> 9.9701517 | H12: =H10+H11 -> 19.727704 | I12: =I10+I11 -> 26.774944 | ... M12: =M10+M11 -> 97.123918
A13: (-) Investimentos / CAPEX | B13: =DFC_A!B10 -> -8 | C13: =DFC_A!C10 -> 0 | D13: =DFC_A!D10 -> 0 | E13: =DFC_A!E10 -> 0 | F13: =DFC_A!F10 -> -24 | G13: =DFC_A!G10 -> 0 | H13: =DFC_A!H10 -> 0 | I13: =DFC_A!I10 -> 0 | ... M13: =DFC_A!M10 -> 0
A14: (=) Fluxo de Caixa Livre | B14: =B12+B13 -> -17.930809 | C14: =C12+C13 -> -3.5440955 | D14: =D12+D13 -> 3.0250955 | E14: =E12+E13 -> 9.411809 | F14: =F12+F13 -> -21.876382 | G14: =G12+G13 -> 9.9701517 | H14: =H12+H13 -> 19.727704 | I14: =I12+I13 -> 26.774944 | ... M14: =M12+M13 -> 97.123918
A15: (+) Financiamento / aporte | B15: =DFC_A!B12 -> 47.414382 | C15: =DFC_A!C12 -> 0 | D15: =DFC_A!D12 -> 0 | E15: =DFC_A!E12 -> 0 | F15: =DFC_A!F12 -> 0 | G15: =DFC_A!G12 -> 0 | H15: =DFC_A!H12 -> 0 | I15: =DFC_A!I12 -> 0 | ... M15: =DFC_A!M12 -> 0
A16: (=) FC do período | B16: =B14+B15 -> 29.483573 | C16: =C14+C15 -> -3.5440955 | D16: =D14+D15 -> 3.0250955 | E16: =E14+E15 -> 9.411809 | F16: =F14+F15 -> -21.876382 | G16: =G14+G15 -> 9.9701517 | H16: =H14+H15 -> 19.727704 | I16: =I14+I15 -> 26.774944 | ... M16: =M14+M15 -> 97.123918
A17: FC Acumulado | B17: =B16 -> 29.483573 | C17: =B17+C16 -> 25.939478 | D17: =C17+D16 -> 28.964573 | E17: =D17+E16 -> 38.376382 | F17: =E17+F16 -> 16.5 | G17: =F17+G16 -> 26.470152 | H17: =G17+H16 -> 46.197855 | I17: =H17+I16 -> 72.972799 | J17: =I17+J16 -> 61.60729 | ... M17: =L17+M16 -> 292.50549
A19: Abertura gerencial para aderência ao E6: 60% do OPEX do cenário A — Bootstrap / Founder-led é apresentado como custo de prestação e 40% como SG&A. O OPEX total não muda. Essa alocação é estimativa até existir folha/centros de custo definitivos.

Sheet E6_DFC_B_Final
A1: ANTÉVIA — E6 | DFC B — Angel / Professional-led | R$ mil
A3: Linha | B3: T1 | C3: T2 | D3: T3 | E3: T4 | F3: T5 | G3: T6 | H3: T7 | I3: T8 | J3: T9 | K3: T10 | L3: T11 | M3: T12
A4: Receita Bruta | B4: =DFC_B!B4 -> 7.1797753 | C4: =DFC_B!C4 -> 14.160112 | D4: =DFC_B!D4 -> 21.339888 | E4: =DFC_B!E4 -> 28.320225 | F4: =DFC_B!F4 -> 56.640449 | G4: =DFC_B!G4 -> 65.216292 | H4: =DFC_B!H4 -> 76.783708 | I4: =DFC_B!I4 -> 85.359551 | ... M4: =DFC_B!M4 -> 223.12017
A5: (-) Impostos sobre receita | B5: =DFC_B!B8 -> -0.43078652 | C5: =DFC_B!C8 -> -0.84960674 | D5: =DFC_B!D8 -> -1.2803933 | E5: =DFC_B!E8 -> -1.6992135 | F5: =DFC_B!F8 -> -3.398427 | G5: =DFC_B!G8 -> -3.9129775 | H5: =DFC_B!H8 -> -5.4331672 | I5: =DFC_B!I8 -> -6.7470112 | ... M5: =DFC_B!M8 -> -25.011052
A6: (-) Custos transacionais | B6: =DFC_B!B5 -> -0.108 | C6: =DFC_B!C5 -> -0.213 | D6: =DFC_B!D5 -> -0.321 | E6: =DFC_B!E5 -> -0.426 | F6: =DFC_B!F5 -> -0.852 | G6: =DFC_B!G5 -> -0.981 | H6: =DFC_B!H5 -> -1.155 | I6: =DFC_B!I5 -> -1.284 | ... M6: =DFC_B!M5 -> -3.354
A7: (-) Perdas operacionais | B7: =DFC_B!B6 -> -0.071797753 | C7: =DFC_B!C6 -> -0.14160112 | D7: =DFC_B!D6 -> -0.21339888 | E7: =DFC_B!E6 -> -0.28320225 | F7: =DFC_B!F6 -> -0.56640449 | G7: =DFC_B!G6 -> -0.65216292 | H7: =DFC_B!H6 -> -0.76783708 | I7: =DFC_B!I6 -> -0.85359551 | ... M7: =DFC_B!M6 -> -2.2312017
A8: (=) Receita Líquida gerencial | B8: =SUM(B4:B7) -> 6.569191 | C8: =SUM(C4:C7) -> 12.955904 | D8: =SUM(D4:D7) -> 19.525096 | E8: =SUM(E4:E7) -> 25.911809 | F8: =SUM(F4:F7) -> 51.823618 | G8: =SUM(G4:G7) -> 59.670152 | H8: =SUM(H4:H7) -> 69.427704 | I8: =SUM(I4:I7) -> 76.474944 | ... M8: =SUM(M4:M7) -> 192.52392
A9: (-) Total de custos | B9: =DFC_B!B7*0.65 -> -34.905 | C9: =DFC_B!C7*0.65 -> -34.905 | D9: =DFC_B!D7*0.65 -> -34.905 | E9: =DFC_B!E7*0.65 -> -34.905 | F9: =DFC_B!F7*0.65 -> -52.65 | G9: =DFC_B!G7*0.65 -> -52.65 | H9: =DFC_B!H7*0.65 -> -52.65 | I9: =DFC_B!I7*0.65 -> -52.65 | ... M9: =DFC_B!M7*0.65 -> -77.61
A10: (=) Contribuição Bruta | B10: =B8+B9 -> -28.335809 | C10: =C8+C9 -> -21.949096 | D10: =D8+D9 -> -15.379904 | E10: =E8+E9 -> -8.993191 | F10: =F8+F9 -> -0.82638202 | G10: =G8+G9 -> 7.0201517 | H10: =H8+H9 -> 16.777704 | I10: =I8+I9 -> 23.824944 | ... M10: =M8+M9 -> 114.91392
A11: (-) Total de despesas (SG&A) | B11: =DFC_B!B7*(1-0.65) -> -18.795 | C11: =DFC_B!C7*(1-0.65) -> -18.795 | D11: =DFC_B!D7*(1-0.65) -> -18.795 | E11: =DFC_B!E7*(1-0.65) -> -18.795 | F11: =DFC_B!F7*(1-0.65) -> -28.35 | G11: =DFC_B!G7*(1-0.65) -> -28.35 | H11: =DFC_B!H7*(1-0.65) -> -28.35 | I11: =DFC_B!I7*(1-0.65) -> -28.35 | ... M11: =DFC_B!M7*(1-0.65) -> -41.79
A12: (=) Resultado operacional de caixa | B12: =B10+B11 -> -47.130809 | C12: =C10+C11 -> -40.744096 | D12: =D10+D11 -> -34.174904 | E12: =E10+E11 -> -27.788191 | F12: =F10+F11 -> -29.176382 | G12: =G10+G11 -> -21.329848 | H12: =H10+H11 -> -11.572296 | I12: =I10+I11 -> -4.5250562 | ... M12: =M10+M11 -> 73.123918
A13: (-) Investimentos / CAPEX | B13: =DFC_B!B10 -> -8 | C13: =DFC_B!C10 -> 0 | D13: =DFC_B!D10 -> 0 | E13: =DFC_B!E10 -> 0 | F13: =DFC_B!F10 -> -24 | G13: =DFC_B!G10 -> 0 | H13: =DFC_B!H10 -> 0 | I13: =DFC_B!I10 -> 0 | ... M13: =DFC_B!M10 -> 0
A14: (=) Fluxo de Caixa Livre | B14: =B12+B13 -> -55.130809 | C14: =C12+C13 -> -40.744096 | D14: =D12+D13 -> -34.174904 | E14: =E12+E13 -> -27.788191 | F14: =F12+F13 -> -53.176382 | G14: =G12+G13 -> -21.329848 | H14: =H12+H13 -> -11.572296 | I14: =I12+I13 -> -4.5250562 | ... M14: =M12+M13 -> 73.123918
A15: (+) Financiamento / aporte | B15: =DFC_B!B12 -> 337.50709 | C15: =DFC_B!C12 -> 0 | D15: =DFC_B!D12 -> 0 | E15: =DFC_B!E12 -> 0 | F15: =DFC_B!F12 -> 0 | G15: =DFC_B!G12 -> 0 | H15: =DFC_B!H12 -> 0 | I15: =DFC_B!I12 -> 0 | ... M15: =DFC_B!M12 -> 0
A16: (=) FC do período | B16: =B14+B15 -> 282.37628 | C16: =C14+C15 -> -40.744096 | D16: =D14+D15 -> -34.174904 | E16: =E14+E15 -> -27.788191 | F16: =F14+F15 -> -53.176382 | G16: =G14+G15 -> -21.329848 | H16: =H14+H15 -> -11.572296 | I16: =I14+I15 -> -4.5250562 | ... M16: =M14+M15 -> 73.123918
A17: FC Acumulado | B17: =B16 -> 282.37628 | C17: =B17+C16 -> 241.63219 | D17: =C17+D16 -> 207.45728 | E17: =D17+E16 -> 179.66909 | F17: =E17+F16 -> 126.49271 | G17: =F17+G16 -> 105.16286 | H17: =G17+H16 -> 93.590566 | I17: =H17+I16 -> 89.065509 | J17: =I17+J16 -> 53.7 | ... M17: =L17+M16 -> 212.5982
A19: Abertura gerencial para aderência ao E6: 65% do OPEX do cenário B — Angel / Professional-led é apresentado como custo de prestação e 35% como SG&A. O OPEX total não muda. Essa alocação é estimativa até existir folha/centros de custo definitivos.

Sheet E6_Pessoal
A1: ANTÉVIA — E6 | Estrutura de Pessoal e Memória de Cálculo
A3: Premissa trabalhista/gerencial | B3: Valor | C3: Unidade | D3: Status | E3: Uso | F3: Observação
A4: Encargos + benefícios sobre salário | B4: 0.4 | C4: % salário | D4: Premissa E6 | E4: Staff contratado | F4: Proxy acadêmica; validar regime/benefícios
A5: Pró-labore caixa founders A1 | B5: 0 | C5: R$/mês | D5: Premissa E6 | E5: Cenário A | F5: Dedicação tratada como sweat equity
A6: Valor econômico founders A1 | B6: 6200 | C6: R$/mês por founder | D6: Premissa herdada | E6: Sweat equity | F6: 2 founders = R$148,8 mil/ano
A7: Meses por ano | B7: 12 | C7: meses | D7: Modelo | E7: Cálculo
A8: Headcount founder A1 | B8: 2 | C8: pessoas | D8: Premissa herdada | E8: Cenário A | F8: Não integra folha caixa A1
A11: Cenário | B11: Ano | C11: Função | D11: Qtd. | E11: Salário mensal | F11: Enc.+benef. | G11: Custo mensal unit. | H11: Custo anual staff | I11: Founders em caixa | J11: Pessoal total caixa | K11: OPEX total existente | L11: OPEX não-pessoal residual | M11: Macroprocesso suportado | N11: Status
A12: A | B12: A1 | C12: Founders — operação/comercial | D12: 0 | E12: 0 | F12: =$B$4 -> 0.4 | G12: =E12*(1+F12) -> 0 | H12: =D12*G12*$B$7 -> 0 | I12: 0 | J12: =SUMIFS($H$12:$H$20,$A$12:$A$20,A12,$B$12:$B$20,B12)+I12 -> 0 | K12: 66000 | L12: =K12-J12 -> 66000 | M12: Aquisição; planejamento; intermediação; concierge; gestão | N12: Premissa E6 — salário a validar
A13: A | B13: A2 | C13: Ops/CS | D13: 1 | E13: 5000 | F13: =$B$4 -> 0.4 | G13: =E13*(1+F13) -> 7000 | H13: =D13*G13*$B$7 -> 84000 | I13: 0 | J13: =SUMIFS($H$12:$H$20,$A$12:$A$20,A13,$B$12:$B$20,B13)+I13 -> 84000 | K13: 198800 | L13: =K13-J13 -> 114800 | M13: Onboarding; planejamento; concierge; exceções; pós-viagem | N13: Premissa E6 — salário a validar
A14: A | B14: A3 | C14: Ops/CS | D14: 2 | E14: 5500 | F14: =$B$4 -> 0.4 | G14: =E14*(1+F14) -> 7700 | H14: =D14*G14*$B$7 -> 184800 | I14: 0 | J14: =SUMIFS($H$12:$H$20,$A$12:$A$20,A14,$B$12:$B$20,B14)+I14 -> 184800 | K14: 381600 | L14: =K14-J14 -> 196800 | M14: Onboarding; planejamento; concierge; exceções; pós-viagem | N14: Premissa E6 — salário a validar
A15: B | B15: A1 | C15: Ops/CS | D15: 1 | E15: 5000 | F15: =$B$4 -> 0.4 | G15: =E15*(1+F15) -> 7000 | H15: =D15*G15*$B$7 -> 84000 | I15: 0 | J15: =SUMIFS($H$12:$H$20,$A$12:$A$20,A15,$B$12:$B$20,B15)+I15 -> 176400 | K15: 214800 | L15: =K15-J15 -> 38400 | M15: Onboarding; planejamento; concierge; exceções; pós-viagem | N15: Premissa E6 — salário a validar
A16: B | B16: A1 | C16: Comercial/Parcerias | D16: 1 | E16: 5500 | F16: =$B$4 -> 0.4 | G16: =E16*(1+F16) -> 7700 | H16: =D16*G16*$B$7 -> 92400 | I16: 0 | J16: =SUMIFS($H$12:$H$20,$A$12:$A$20,A16,$B$12:$B$20,B16)+I16 -> 176400 | K16: 214800 | L16: =K16-J16 -> 38400 | M16: Aquisição; escolas/parceiros; relacionamento | N16: Premissa E6 — salário a validar
A17: B | B17: A2 | C17: Ops/CS | D17: 2 | E17: 5250 | F17: =$B$4 -> 0.4 | G17: =E17*(1+F17) -> 7350 | H17: =D17*G17*$B$7 -> 176400 | I17: 0 | J17: =SUMIFS($H$12:$H$20,$A$12:$A$20,A17,$B$12:$B$20,B17)+I17 -> 277200 | K17: 324000 | L17: =K17-J17 -> 46800 | M17: Onboarding; planejamento; concierge; exceções; pós-viagem | N17: Premissa E6 — salário a validar
A18: B | B18: A2 | C18: Comercial/Parcerias | D18: 1 | E18: 6000 | F18: =$B$4 -> 0.4 | G18: =E18*(1+F18) -> 8400 | H18: =D18*G18*$B$7 -> 100800 | I18: 0 | J18: =SUMIFS($H$12:$H$20,$A$12:$A$20,A18,$B$12:$B$20,B18)+I18 -> 277200 | K18: 324000 | L18: =K18-J18 -> 46800 | M18: Aquisição; escolas/parceiros; relacionamento | N18: Premissa E6 — salário a validar
A19: B | B19: A3 | C19: Ops/CS | D19: 2 | E19: 5750 | F19: =$B$4 -> 0.4 | G19: =E19*(1+F19) -> 8050 | H19: =D19*G19*$B$7 -> 193200 | I19: 0 | J19: =SUMIFS($H$12:$H$20,$A$12:$A$20,A19,$B$12:$B$20,B19)+I19 -> 310800 | K19: 477600 | L19: =K19-J19 -> 166800 | M19: Onboarding; planejamento; concierge; exceções; pós-viagem | N19: Premissa E6 — salário a validar
A20: B | B20: A3 | C20: Comercial/Parcerias | D20: 1 | E20: 7000 | F20: =$B$4 -> 0.4 | G20: =E20*(1+F20) -> 9800 | H20: =D20*G20*$B$7 -> 117600 | I20: 0 | J20: =SUMIFS($H$12:$H$20,$A$12:$A$20,A20,$B$12:$B$20,B20)+I20 -> 310800 | K20: 477600 | L20: =K20-J20 -> 166800 | M20: Aquisição; escolas/parceiros; relacionamento | N20: Premissa E6 — salário a validar
A24: Cenário/Ano | B24: HC staff | C24: Custo staff | D24: Founders caixa | E24: Pessoal caixa | F24: OPEX não-pessoal | G24: OPEX total | H24: Check | J24: Sweat equity A1 | K24: Qtd founders | L24: Valor mensal | M24: Meses | N24: Valor anual
A25: A/A1 | B25: =SUMIFS($D$12:$D$20,$A$12:$A$20,"A",$B$12:$B$20,"A1") -> 0 | C25: =SUMIFS($H$12:$H$20,$A$12:$A$20,"A",$B$12:$B$20,"A1") -> 0 | D25: 0 | E25: =C25+D25 -> 0 | F25: =G25-E25 -> 66000 | G25: 66000 | H25: =IF(ABS(E25+F25-G25)<1,"OK","REVER") -> OK | J25: Founder-led A1 | K25: 2 | L25: 6200 | M25: 12 | N25: =K25*L25*M25 -> 148800
A26: A/A2 | B26: =SUMIFS($D$12:$D$20,$A$12:$A$20,"A",$B$12:$B$20,"A2") -> 1 | C26: =SUMIFS($H$12:$H$20,$A$12:$A$20,"A",$B$12:$B$20,"A2") -> 84000 | D26: 0 | E26: =C26+D26 -> 84000 | F26: =G26-E26 -> 114800 | G26: 198800 | H26: =IF(ABS(E26+F26-G26)<1,"OK","REVER") -> OK
A27: A/A3 | B27: =SUMIFS($D$12:$D$20,$A$12:$A$20,"A",$B$12:$B$20,"A3") -> 2 | C27: =SUMIFS($H$12:$H$20,$A$12:$A$20,"A",$B$12:$B$20,"A3") -> 184800 | D27: 0 | E27: =C27+D27 -> 184800 | F27: =G27-E27 -> 196800 | G27: 381600 | H27: =IF(ABS(E27+F27-G27)<1,"OK","REVER") -> OK
A28: B/A1 | B28: =SUMIFS($D$12:$D$20,$A$12:$A$20,"B",$B$12:$B$20,"A1") -> 2 | C28: =SUMIFS($H$12:$H$20,$A$12:$A$20,"B",$B$12:$B$20,"A1") -> 176400 | D28: 0 | E28: =C28+D28 -> 176400 | F28: =G28-E28 -> 38400 | G28: 214800 | H28: =IF(ABS(E28+F28-G28)<1,"OK","REVER") -> OK
A29: B/A2 | B29: =SUMIFS($D$12:$D$20,$A$12:$A$20,"B",$B$12:$B$20,"A2") -> 3 | C29: =SUMIFS($H$12:$H$20,$A$12:$A$20,"B",$B$12:$B$20,"A2") -> 277200 | D29: 0 | E29: =C29+D29 -> 277200 | F29: =G29-E29 -> 46800 | G29: 324000 | H29: =IF(ABS(E29+F29-G29)<1,"OK","REVER") -> OK
A30: B/A3 | B30: =SUMIFS($D$12:$D$20,$A$12:$A$20,"B",$B$12:$B$20,"A3") -> 3 | C30: =SUMIFS($H$12:$H$20,$A$12:$A$20,"B",$B$12:$B$20,"A3") -> 310800 | D30: 0 | E30: =C30+D30 -> 310800 | F30: =G30-E30 -> 166800 | G30: 477600 | H30: =IF(ABS(E30+F30-G30)<1,"OK","REVER") -> OK
A34: IMPORTANTE: os salários e a carga de 40% são premissas gerenciais criadas para abrir o OPEX agregado já existente; não foram encontrados, nas fontes do projeto, salários contratados, benefícios definidos ou regime trabalhista fechado. Por isso a planilha calcula o OPEX não-pessoal como residual e preserva exatamente os totais financeiros já aprovados no modelo. No cenário A/A1, os dois founders não recebem pró-labore em caixa; seu valor econômico de R$148,8 mil/ano permanece tratado separadamente como sweat equity.
